Workbook
Name Code: Liste!$A$2:$A$275
Name Description: Liste!$B:$B
Name Prix: Liste!$F$2:$F$275

Sheet Liste
A1: Code | B1: nom | C1: Fournisseur principal | D1: INCI | E1: Catégorie | F1: Prix au kilo | G1: En stock | H1: Remarques et cotations | I1: %PPAI | J1: %PPAI Bio | K1: %CPAI | L1: %CPAI Bio | M1: Fonctions | N1: N°CAS | O1: Impuretés
B2: SustOleo TSB | C2: Inolex | D2: Hydrogenated Rapeseed oil | E2: Co-émulsionnant O/W | H2: Sans palme, 100% NAT, équivalent au beurre de karité, stabilise l'émulsion sans recristalliser (pf = 67°C), apporte de la richesse à l'émulsion
A3: ECH-AMB001 | B3: Ambrette CO2 | C3: Aroma Zone | E3: Extrait CO2
A4: ECH-AMB002 | B4: HE Ambrette | C4: Diffusions Aromatiques | E4: Huile essentielle | F4: 7500
A5: ECH-AMB003 | B5: Ambrette graines extrait CO2 | C5: Diffusions Aromatiques | E5: Extrait CO2
A6: ECH-AMY001 | B6: Amyris | C6: Astier Demarest | E6: Huile essentielle
A7: ECH-AP001 | B7: Poudre d'avoine colloïdale | C7: Aroma Zone | E7: Actif poudre
A8: ECH-AP002 | B8: Lait d'amande douche en poudre | C8: Aroma Zone
A9: ECH-AP003 | B9: Lait de coco en poudre | C9: Aroma Zone
A10: ECH-AP004 | B10: Nelumbo nucifera seeds (poudre) | C10: BPAE
A11: ECH-AP005 | B11: Curcuma Longa Rhizome | C11: BPAE
A12: ECH-AP006 | B12: Natural anhydrous caffeine powder | C12: Naturex | G12: Non
A13: ECH-AP007 | B13: Rutin 95% | C13: Naturex | F13: 254.1 | H13: 254,10(1kg), 182,20(10kg). % utilisation : max 0,5%. pH : from 2 to 7. Solubility : 1% (10% d'après leur labo) in hot glycerin for clear product - In surfactant or aqueous systems: add the blend at the end of the process - In emulsion: add the blend at the end after 40°C.
A14: ECH-AP008 | B14: Poudre Aloe vera BIO | C14: IES Labo
A15: ECH-AP009 | B15: Guarana PE 2,4% Caffeine | C15: Naturex | G15: Non
A16: ECH-AP010 | B16: Spiruline poudre | C16: ? | G16: Non
A17: ECH-AP011 | B17: L-Arginine | C17: Inolex | G17: Non
A18: ECH-AP012 | B18: Moringa poudre | C18: ?
A19: ECH-AP013 | B19: Oxyde de Zinc | C19: Aroma Zone
A20: ECH-AP014 | B20: Lavande fleurs poudre BIO | C20: L'Herbier du Diois
A21: ECH-AP015 | B21: Tomate poudre BIO | C21: L'Herbier du Diois
A22: ECH-AP016 | B22: Bardane racine poudre BIO | C22: L'Herbier du Diois
A23: ECH-AP017 | B23: Réglisse racine poudre BIO | C23: L'Herbier du Diois
A24: ECH-AP018 | B24: Mauve PA poudre BIO | C24: L'Herbier du Diois
A25: ECH-AP019 | B25: Moga Cha BIO | C25: Alveus
A26: ECH-AP020 | B26: Curcuma poudre BIO | C26: L'Herbier du Diois
A27: ECH-AP021 | B27: Iris pâle PA poudre BIO | C27: L'Herbier du Diois
A28: ECH-AP022 | B28: Eucalyptus feuille poudre BIO | C28: L'Herbier du Diois
A29: ECH-AP023 | B29: Citron zeste poudre BIO | C29: L'Herbier du Diois
... A34: ECH-AP028 | B34: Guimauve racine poudre BIO | C34: L'Herbier du Diois
A35: ECH-AP029 | B35: Oat Phylpeel 2000T | C35: Safic Alcan | D35: Avena Sativa Kernel Extract | E35: Flocons | F35: 50
A36: ECH-AP030 | B36: Oat Phylpeel 1000T | C36: Safic Alcan | D36: Avena Sativa Kernel Extract | E36: Flocons | F36: 50
A37: ECH-AP033 | B37: Glucohyami-SAE (Maintenant Glucohyami GL) | C37: Alban Muller | F37: 104.56€/kg (par 25kg), 114.39€/kg (par 5kg) | G37: Non
A38: ECH-AP034 | B38: Sel de la mer morte | C38: Aroma Zone
A39: ECH-AP035 | B39: Farine de café unmilled | C39: Caffe Bueno
A40: ECH-AP036 | B40: Farine de café milled | C40: Caffe Bueno
A41: ECH-AP037 | B41: Argile grade surfine
A42: ECH-AP038 | B42: Kaolin Imercare Opaque
A43: ECH-AP039 | B43: Pigment végétal Rose Patate douce | C43: Aroma Zone | D43: Distarch Phosphate, Anthocyanins, Citric Acid | E43: Colorant
A44: ECH-AP040 | B44: SpecWhite 02 | C44: Maprecos | D44: Ascorbyl Glucoside | E44: Vitamine C forme stable | H44: Attention peut devenir orange (restaer à un pH de 6,5)
A45: ECH-AP041 | B45: Specpure GBE001 | C45: Maprecos | D45: Sodium Copper Chlorophyllin | E45: Colorant | G45: Non
A46: ECH-AP042 | B46: Vanilla Exfoliating soft Powder | C46: Pacifique Sud | E46: Exfoliant physique
A47: ECH-AP043 | B47: Spent Bourbon vanilla seeds | C47: Euro Vanille | E47: Graines odorantes | F47: 110 | G47: Non
A48: ECH-AP044 | B48: Grains naturels de vanille Bourbon | C48: Euro Vanille | F48: 460 | G48: Non
A49: ECH-AP045 | B49: SpecPure BML60 | C49: Maprecos | D49: Bromelain 60W | E49: Enzyme | H49: Bromélaine, enzyme issue de l’ananas. Peeling chimique, blanchissant
A50: ECH-AP046 | B50: Promois | C50: Iwase | D50: Hydrolyzed Pea Proten | E50: Protéine de pois | G50: Non
A51: ECH-AP047 | B51: Spirulina ET-F | C51: Maprecos | E51: Spiruline poudre
A52: ECH-AP048 | B52: Linablue G1-S | C52: Maprecos | E52: Colorant spiruline
A53: ECH-AP049 | B53: Spiruline bio poudre | C53: Azur Naturel | E53: Spiruline poudre
A54: ECH-AP050 | B54: CBP Inulin FOS | C54: DKSH | D54: Inulin | E54: Inuline poudre | F54: 30.5
A55: ECH-AP051 | B55: Noyaux d'olive en poudre | C55: Aroma-Zone | E55: Exfoliant physique
A56: ECH-AP052 | B56: Noyaux d'abricot en poudre | C56: Aroma-Zone | E56: Exfoliant physique
A57: ECH-AP053 | B57: Coque de noix en poudre | C57: Aroma-Zone | E57: Exfoliant physique
A58: ECH-AP054 | B58: Charbon Végétal Active poudre | C58: Herboristerie Cailleau | E58: Poudre | F58: 53.9
A59: ECH-AP055 | B59: Charbon végétal poudre (usage externe) | C59: Herboristerie Cailleau | E59: Poudre | F59: 16
A60: ECH-AP056 | B60: Charbon végétal active 400-600um | C60: Herboristerie Cailleau | E60: Exfoliant physique | F60: 53.9
A61: ECH-AP057 | B61: Poudre charbon végétal | C61: Prod'hyg | E61: Exfoliant physique
A62: ECH-AP058 | B62: Charbon actif végétal 100-300 micron BIO | C62: Exinnov
A63: ECH-AP059 | B63: Seatrace | C63: Lessonia | D63: Maris Sal | E63: Poudre reminéralisante | F63: 14.7 | H63: Sel avec faible taux de NaCl, reminéralisant. Concentrée en oligoéléments et minéraux
A64: ECH-AP060 | B64: Bio Microzest 50 Laminaria | C64: Lessonia | D64: Laminaria digitata powder | F64: 12.42
A65: ECH-AP061 | B65: Green Microzest 50 Red Clay | C65: Lessonia | D65: Illite, Kaolin | E65: Argile | F65: 16
A66: ECH-AP062 | B66: Olive GreenExfoliator 500 | C66: Lessonia | D66: Olea Europaea seed powder | E66: Exfoliant physique | F66: 28.71
A67: ECH-AP063 | B67: Bitter Orange Exfoliator 1000 | C67: Lessonia | D67: Citrus Anrantium Amara peel powder | E67: Exfoliant physique | F67: 32.13
A68: ECH-AP064 | B68: Lemon Exfoliator 1000 | C68: Lessonia | D68: Citrus Lemon peel powder | E68: Exfoliant physique | F68: 45.15
A69: ECH-AP065 | B69: Lemon Exfoliator 500 | C69: Lessonia | D69: Citrus Lemon peel powder | E69: Exfoliant physique | F69: 45.15
A70: ECH-AP066 | B70: C+eramide G | C70: Lessonia | D70: Triticum vulgare (wheat) seed extract | E70: Poudre active | F70: 1417.5
A71: ECH-AP067 | B71: Poudre de Banane | C71: Aroma-Zone
A72: ECH-AP068 | B72: Erylite F8030 | C72: AMI | D72: Erythritol | F72: 7.12
A73: ECH-AP069 | B73: Tricalcium Citrate | C73: AMI | D73: Calcium Citrate
A74: ECH-AP070 | B74: Gluadin WP | C74: AMI | D74: Hydrolyzed Wheat Protein
A75: ECH-AP071 | B75: Glucono-Delta-Lactone | C75: AMI | D75: Gluconolactone | F75: 6.16
A76: ECH-AP072 | B76: Coenzym Q10 MP009 | C76: Azelis | D76: Ubiquinone | F76: 1392 | I76: 0 | J76: 0 | K76: 99.8 | L76: 0
A77: ECH-AP073 | B77: Granulated sugar standard 500-950 microns | C77: DKSH | D77: Saccharose | E77: Exfoliant physique
A78: ECH-AP074 | B78: Pierre ponce doux | C78: DKSH | D78: Pumice | E78: Exfoliant physique | G78: Non
A79: ECH-AP075 | B79: Pierre ponce fort | C79: DKSH | D79: Pumice | E79: Exfoliant physique | G79: Non
A80: ECH-AP076 | B80: Pierre ponce stimulant | C80: DKSH | D80: Pumice | E80: Exfoliant physique | G80: Non
A81: ECH-AP077 | B81: Opuntia Biocomplex SH | C81: Interactifs | D81: Opuntia ficus-indica stem extract, Maltodextrin | E81: Actif prébiotique | F81: 131.23 | H81: 0,5 et 5% Ratio = 1:25 Microbiome-friendly formulations Skin care and hair care products for dry and sensitive skin Skin repair Co-adjuvant in anti-dandruff shampoo Cosmetic products for acne-prone skin
A82: ECH-AP078 | B82: Maizena | C82: Maizena Fleur de Mais
A83: ECH-AP079 | B83: Sodium Gluconate | C83: AMI | D83: Sodium Gluconate
A84: ECH-AP080 | B84: Thixcin R PC | C84: Elementis-DKSH | D84: Trihydroxystearin
A85: ECH-AP081 | B85: Bentone Hydroclay 2100 | C85: Elementis-DKSH | D85: Hectorite
A86: ECH-AP082 | B86: Urée | C86: Aroma Zone | D86: Urea | E86: Exfoliant chimique | H86: Très utilisée en cosmétique et dans les préparations dermatologiques, l'urée est connue pour ses propriétés hydratantes* intenses et son effet kératolytique. Elle s'incorpore dans vos préparations cosmétiques pour favoriser l'élimination des squames et redonner souplesse et douceur aux peaux très sèches, rugueuses ou squameuses. Son pouvoir exfoliant doux et son excellente tolérance cutanée en font également une bonne alternative aux AHA acides de fruits pour lisser les irrégularités de la peau et redonner de l'éclat au teint. C'est aussi l'actif de choix pour traiter les callosités sur les pieds ou les mains. Un actif de base très professionnel ! *hydratation des couches supérieures de l'épiderme.
A87: ECH-AP083 | B87: Bentone HydroClay 2000 | C87: DKSH | D87: Hectorite
A88: ECH-AP084 | B88: Plankton Glass Flower | C88: ODYCEA | D88: Plankton extract | E88: Agent soft-focus | H88: Poudre dispersible dans l'eau et l'huile. % utilisation : 1-3% | I88: 100 | J88: 0 | K88: 0 | L88: 0
A89: ECH-AP085 | B89: Cellulobeads USF-X | C89: Daito Kasei | D89: Cellulose | E89: Effet blur, agent soft-focus et de couvrance (slip modifier) | F89: 213 | H89: Hydrophile. Incorporer une fois l'émulsion/gel formé. Incorporer à 10% maximum. COSMOS. 100% cellulose obtained from wood pulp 213(20kg); 191,6(100kg); 182(400kg) | K89: 100
A90: ECH-AP086 | B90: Easyliance | C90: Givaudan | D90: Acacia Senegal gum Rhizobian gum | E90: Effet liftant | F90: 304.1 | H90: Hydrosoluble. % utilisation : 2-3%. Incorporer au début ou à la fin de la formulation entre 20 et 80 °C sous agitation douce. pH : 2-8
A91: ECH-AP087 | B91: Vit-a-like PW LS 9898 (Retinol-like) | C91: BASF/AMI | D91: Vigna Aconitifolia Seed Extract (and) Maltodextrin | E91: Extrait de la graine de haricot papillon | F91: 699.9 | H91: Rétinol-like. Hydrosoluble. %utilisation : 0,2-0,4%. Réaliser une solution en amont à 10% dans l'eau avant de l'incorporer dans la phase finale en dessous de 60°C. Optimal pH: 3 - 8 MOQ = 0,5kg | I91: 70 | K91: 30
A92: ECH-AP088 | B92: Oxyde Bleu | C92: Aroma Zone | D92: Ultramarine, Silica and Kaolin | E92: Pigment minéral
A93: ECH-AP089 | B93: Primalhyal 10 | C93: Givaudan | D93: Hydrolyzed Hyaluronic Acid | E93: Actif | H93: < à 10KDa Représente notre acide hyaluronique nano | K93: 100
A94: ECH-AP090 | B94: Cristalyal | C94: Givaudan | D94: Sodium Hyaluronate | E94: Actif | F94: 1510 | H94: 1M à 1,4MDa Représente notre MP007 | K94: 100
A95: ECH-AP091 | B95: Primalhyal 50 | C95: Givaudan | D95: Hydrolyzed Hyaluronic Acid | E95: Actif | F95: 1920 | H95: 50KDa Représente notre 10K MP006 (10-100KDa) | K95: 100
A96: ECH-AP092 | B96: Poudre exfoliante de noyau de pruneau Bio <300µ | C96: Perles de Gascogne | D96: Organic Exfoliant Plum Kernel Powder | E96: Exfoliant | F96: 17 | H96: 25kg
A97: ECH-AP093 | B97: Poudre exfoliante de noyau de pruneau Bio 300<>500µ | C97: Perles de Gascogne | D97: Organic Exfoliant Plum Kernel Powder | E97: Exfoliant | F97: 18.5 | H97: 25kg
A98: ECH-AP094 | B98: Poudre exfoliante de noyau de pruneau Bio 500<>800µ | C98: Perles de Gascogne | D98: Organic Exfoliant Plum Kernel Powder | E98: Exfoliant | F98: 18.5 | H98: 25kg
A99: ECH-AP096 | B99: Green Microzest 25 Bamboo | C99: Lessonia | D99: Bambusa Arundinacea Stem Extract | E99: Exfoliant | F99: 51
A100: ECH-AP097 | B100: Azelaic Acid | C100: Safic Alcan | D100: Azelaic Acid | E100: Exfoliant chimique
A101: ECH-AP098 | B101: Phytolive Fine | C101: Sophim | E101: Exfoliant physique | H101: Exfoliant fait à partir de noyaux d'olive. Testé rapidement dans une crème, gratte bien !
A102: ECH-AP099 | B102: Café grain | C102: ? | E102: Exfoliant physique
A103: ECH-AP100 | B103: Coconut Milk Powder | C103: From Nature With Love | D103: Cocos Nucifera Fruit Powder (and) Maltodextrin (and) Sodium Starch Octenylsuccinate (Modified Food Starch) | E103: Lait poudre
A104: ECH-AP101 | B104: Neosalyl | C104: Givaudan / Quimica Masso | D104: Salicylic Acid | E104: Exfoliant chimique | F104: 330 | H104: 1kg =>364€ 5kg => 330€ 10=> 321€
...

Sheet Descriptions
B3: ECH-AP | C3: Actifs poudre | E3: Mise à jour prix MP : le 5.02.2024
B4: ECH-CON | C4: Conservateurs
B5: ECH-HBC | C5: Huiles, beurres et cires
B6: ECH-HY | C6: Hydrolats
B7: ECH-LIQ | C7: Actifs liquides
B8: ECH-PAR | C8: Parfums
B9: ECH-TAR | C9: Tensioactifs, MP de rhéologie
B10: ECH-XXX001 | C10: Huile essentielle (avec 3 premières lettres)
B13: MP00 | C13: Actifs techniques objectivés
B14: MP100 | C14: Huiles végétales
B15: MP150 | C15: Esters
B16: MP200 | C16: Hydrolats
B17: MP300 | C17: Moussants
... B25: MP1000IN | C25: Infusion maison
B28: Pour l'onglet emballage :
B29: ECH-EMB | C29: échantillon d'emballage

Sheet Code formule
A1: OF | B1: Nom OF
A2: F001 | B2: MASQUE EXFOLIANT AUX ACIDES DE FRUITS
A3: F001B | B3: MASQUE EXFOLIANT AUX ACIDES DE FRUITS REFORMULATION
A4: F002 | B4: HUILE INTENSE DÉMAQUILLANTE AUX ANTIOXYDANTS
A5: F002B | B5: HUILE INTENSE DÉMAQUILLANTE AUX ANTIOXYDANTS
A6: F003
A7: F004 | B7: CRÈME REVEIL MULTIVITAMINÉE
A8: F005 | B8: CRÈME CONCENTRÉE AUX ACTIFS REPULPANTS
A9: F006 | B9: SÉRUM OLÉAGINEUX ULTRA-NOURISSANT
A10: F007 | B10: BRUME AUX ACTIFS ANTI-POLLUTION
A11: F008 | B11: CRÈME DE NUITS AUX ACTIFS OXYGÉNANTS
A12: F009 | B12: HUILE DU TIGRE MASSAGE POUR SPORTIFS
A13: F010 | B13: BONNE NUIT GEL DOUCHE
A14: F011 | B14: SÉRUM SUPER PLANTES ANTIOXYDANTES
A15: F012 | B15: BRUME HYDRATANTE AUX FLEURS MÉDITERRANÉENNES
A16: F013 | B16: LOTION PERFECTION AUX ACTIFS ASSAINISSANTS
A17: F014 | B17: SÉRUM SYNERGIE ESSENTIELLE PURIFIANT
A18: F015 | B18: L'AMANDIER HUILE CORPS ET CHEVEUX
... A26: F023 | B26: FLUIDE PEAU PARFAITE
A27: F024
A28: F025 | B28: LAIT DOUCEUR VANILLE NETTOYANT
A29: F026 | B29: HUILE DOUCE AUX FLEURS DÉMAQUILLANTE ET NETTOYANTE
A30: F026B | B30: HUILE DOUCE AUX FLEURS DÉMAQUILLANTE ET NETTOYANTE
A31: F027 | B31: MOUSSE DOUCEUR NETTOYANTE ANTI-TIRAILLEMENT
A32: F028
A33: F029 | B33: SUCRE VANILLÉ GOMMAGE GOURMAND POUR LE CORPS
A34: F030 | B34: HUILE DES ILES
A35: F031 | B35: SÉRUM ILLUMINATEUR DE LA ROSERAIE
A36: F031B | B36: SÉRUM ILLUMINATEUR DE LA ROSERAIE B
A37: F032 | B37: MASQUE ROSE LACTÉ APAISANT
A38: F033 | B38: SÉRUM CONCENTRÉ DE SOLEIL
A39: KID034 | B39: GELEE LAVANTE FLEUR VANILLEE
A40: KID035 | B40: BAUME FONDANT MAMAN BÉBÉ
A41: F036 | B41: SOIN LISSANT AUX FLEURS
A42: F037 | B42: GEL REVEIL ANTI-CERNES
A43: KID038 | B43: LA CREME DES BEBES
A44: KID039 | B44: POMMADE MAGIQUE
... A53: F048 | B53: GOMMAGE NOURRISSANT SUCRE VANILLE

Sheet Code MO
A1: Code | B1: Description | C1: Prix unitaire 2024 en € | D1: Coût par pdt
A2: MOFAB001 | B2: Fabrication Huile avec chauffe | C2: =2.3*33.84 -> 77.832 | D2: NA
A3: MOFAB002 | B3: Fabrication Huile sans chauffe | C3: =1.3*33.84 -> 43.992 | D3: NA
A4: MOFAB003 | B4: Fabrication émulsion | C4: =6*33.84 -> 203.04 | D4: NA
A5: MOFAB004 | B5: Fabrication gel aqueux (type gelée noire) | C5: =6*33.84 -> 203.04 | D5: NA
A6: MOFAB005 | B6: Fabrication gel aqueux chauffe (type masque exfoliant) | C6: =4*33.84 -> 135.36 | D6: NA
A7: MOFAB006 | B7: Fabrication lotion non chauffée (brume) | C7: =3*33.84 -> 101.52 | D7: NA
A8: MOFAB007 | B8: Fabrication gel douche avec chauffe | C8: =4*33.84 -> 135.36 | D8: NA
A9: MOFAB008 | B9: Fabrication lotion chauffée (type brume, mousse) | C9: =4*33.84 -> 135.36 | D9: NA
A10: MOCOND001 | B10: Conditionnement airless 50ml (2200pcs) | C10: 198.66 | D10: =C10/2200 -> 0.0903
A11: MOCOND002 | B11: Conditionnement flacon 120ml avec pré-remplissage (1000pcs) | C11: 142 | D11: =C11/1000 -> 0.142
A12: MOCOND0021 | B12: Conditionnement flacon 50ml avec pré-remplissage (2400pcs) | C12: =142*2 -> 284 | D12: =C12/2400 -> 0.11833333
A13: MOCOND003 | B13: Conditionnement sérum 15ml (8000pcs) | C13: 170 | D13: =C13/8000 -> 0.02125
A14: MOCOND004 | B14: Conditionnement flacon 120ml (1000pcs) | C14: 71 | D14: =C14/1000 -> 0.071
A15: MOCOND005 | B15: Conditionnement flacon 200ml (500pcs) | C15: 71 | D15: =C15/500 -> 0.142
A16: MOCOND006 | B16: Conditionnement flacon 200ml avec pré-remplissage (500pcs) | C16: 142 | D16: =C16/500 -> 0.284
A17: MOCOND007 | B17: Conditionnement flacon 120ml ac difficulté (vrac bullée)(1000pcs) | C17: 100 | D17: =C17/1000 -> 0.1
A18: MOCOND008 | B18: Conditionnement flacon 115ml mousse (1000pcs) | C18: 71 | D18: =C18/1000 -> 0.071
A19: MOCOND009 | B19: Conditionnement flacon 5ml bille (2000pcs) | C19: 200 | D19: =C19/2000 -> 0.1

Sheet Emballages
A1: Code emballage | B1: Description emballage | C1: Fournisseurs | D1: Prix unitaire | E1: Catégorie | F1: Remarque
A2: BILLEINO5 | B2: Bille roll on inox 5ml | C2: Esobea | D2: 0.2
A3: CAAE008 | B3: ETUI AAE008 | C3: LECAGRAPHICS | D3: 0.2361
A4: CAAE032 | B4: ETUI AAE032 | C4: LECAGRAPHICS | D4: 0.2361
A5: CANO001 | B5: ETUI ANO001 | C5: LECAGRAPHICS | D5: 0.2361
A6: CANO001B | B6: ETUI ANO001B | C6: VIMER
A7: CANO004 | B7: ETUI ANO004 | C7: LECAGRAPHICS | D7: 0.2361
A8: CANO011 | B8: ETUI ANO011 | C8: LECAGRAPHICS | D8: 0.46712
A9: CANO033 | B9: ETUI ANO033 | C9: LECAGRAPHICS | D9: 0.46712
A10: CAP001-120 | B10: POMPE FLACON 120 ml | C10: YUYAO H.B.PACKAGING CO.,LTD. | D10: 0.11
A11: CAP002-120 | B11: SPRAY FLACON 120 ml | C11: YUYAO H.B.PACKAGING CO.,LTD. | D11: 0.056
A12: CAP002-50 | B12: SPRAY FLACON 50 ml | C12: YUYAO H.B.PACKAGING CO.,LTD. | D12: 0.056
A13: CAP003 | B13: BOUCHON CHAPEAU CHINOIS | C13: YUYAO H.B.PACKAGING CO.,LTD. | D13: 0.025
A14: CAP004 | B14: POMPE AUTO BLOQUANTE 24/410 BLANCHE | C14: SILGAN | D14: 0.35
A15: CAPAIR50 | B15: Airless bouchon 50ml | C15: APTAR | D15: 0.383
A16: CAPFOAM115 | B16: FOAM PUMP MILKY WHITE | C16: TALENTS PACKING INTERNATIONAL LIMITED | D16: 0.25
A17: CAPPIPETTE | B17: Compte goutte pipette | C17: Esobea | D17: 0.28
A18: CAPPIPETTE05 | B18: Compte goutte pipette 5 ml | C18: EUROVETROCAP | D18: 0.27175
... A39: CPUR023 | B39: ETUI PUR023 | C39: LECAGRAPHICS | D39: 0.2361
A40: CPUR041 | B40: ETUI PUR041 | C40: VIMER
A41: CREG005 | B41: ETUI REG005 | C41: LECAGRAPHICS | D41: 0.2361
A42: CREG006 | B42: ETUI REG006 | C42: LECAGRAPHICS | D42: 0.46712
A43: CREG036 | B43: ETUI REG036 | C43: VIMER | D43: 0.4
A44: DAAE027 | B44: DOYPACK AAE027 250 ml | C44: Sealester | D44: 0.62
A45: DHYD025 | B45: DOYPACK HYD025 250 ml | C45: Sealester | D45: 0.62
A46: DPUR016 | B46: DOYPACK PUR016 250 ml | C46: Sealester | D46: 0.62
A47: DPUR017 | B47: DOYPACK PUR017 250 ml | C47: Sealester | D47: 0.62
A48: EAAE007 | B48: ETIQUETTE EAAE007 | C48: LABEL IMPRIME | D48: 0.2287
A49: EAAE008 | B49: ETIQUETTE AAE008 | C49: LABEL IMPRIME | D49: 0.072
A50: EAAE027 | B50: ETIQUETTE AAE027 | C50: LABEL IMPRIME | D50: 0.159
A51: EAAE032 | B51: ETIQUETTE AAE032 | C51: LABEL IMPRIME | D51: 0.072
A52: EAAEV007 | B52: ETIQUETTE EAAVE007 | C52: LABEL IMPRIME | D52: 0.1355
A53: EANO001 | B53: ETIQUETTE ANO001 | C53: LABEL IMPRIME | D53: 0.007737
A54: EANO001B | B54: ETIQUETTE ANO001B | C54: LABEL IMPRIME
A55: EANO002 | B55: ETIQUETTE ANO002 | C55: LABEL IMPRIME | D55: 0.0932
A56: EANO004 | B56: ETIQUETTE ANO004 | C56: LABEL IMPRIME | D56: 0.072
A57: EANO011 | B57: ETIQUETTE ANO011 | C57: LABEL IMPRIME | D57: 0.1
A58: EANO033 | B58: ETIQUETTE ANO033 | C58: LABEL IMPRIME | D58: 0.1
A59: EANOV002 | B59: ETIQUETTE ANOV002 | C59: LABEL IMPRIME | D59: 0.1355
A60: EANOV011 | B60: ETIQUETTE ANOV011 | C60: LABEL IMPRIME | D60: 0.04
A61: EANOV033 | B61: ETIQUETTE ANOV033 | C61: LABEL IMPRIME | D61: 0.04
A62: ECH-EMB001 | B62: Bottle Laurel 50ml avec vernis UV | C62: Glasmeister | D62: 1.05
A63: ECH-EMB002 | B63: Bottle Laurel 50ml | C63: Glasmeister | D63: 0.55
A64: ECH-EMB003 | B64: Jar Lime 50ml | C64: Glasmeister | D64: 0.35
A65: ECH-EMB004 | B65: Jar Lime 50ml avec vernis UV | C65: Glasmeister | D65: 0.45
A66: ECH-EMB005 | B66: Lotion pump metropolitan 24-410 blanc | C66: Glasmeister | D66: 0.79
... A88: EHYDV031 | B88: ETIQUETTE HYDV031 | C88: LABEL IMPRIME | D88: 0.04
A89: EKID034 | B89: ETIQUETTE KID034 | C89: LABEL IMPRIME
A90: EKID035 | B90: ETIQUETTE KID035 | C90: LABEL IMPRIME
A91: EKID038 | B91: ETIQUETTE KID038 | C91: LABEL IMPRIME
A92: EKID040 | B92: ETIQUETTE KID040 | C92: LABEL IMPRIME
A93: EKIDV034 | B93: ETIQUETTE VOYAGE KID034 | C93: LABEL IMPRIME
A94: EKIDV040 | B94: ETIQUETTE VOYAGE KID040 | C94: LABEL IMPRIME
A95: EPUR013 | B95: ETIQUETTE PUR013 | C95: LABEL IMPRIME | D95: 0.159
A96: EPUR014 | B96: ETIQUETTE PUR014 | C96: LABEL IMPRIME | D96: 0.1
A97: EPUR016 | B97: ETIQUETTE PUR016 | C97: LABEL IMPRIME | D97: 0.159
A98: EPUR017 | B98: ETIQUETTE PUR017 | C98: LABEL IMPRIME | D98: 0.159
A99: EPUR023 | B99: ETIQUETTE PUR023 | C99: LABEL IMPRIME | D99: 0.072
A100: EPUR041 | B100: ETIQUETTE PUR041 | C100: LABEL IMPRIME
A101: EPURV013 | B101: ETIQUETTE PURV013 | C101: LABEL IMPRIME | D101: 0.12
A102: EPURV014 | B102: ETIQUETTE PURV014 | C102: LABEL IMPRIME | D102: 0.04
A103: EREG005 | B103: ETIQUETTE REG005 | C103: LABEL IMPRIME | D103: 0.07737
A104: EREG006 | B104: ETIQUETTE REG006 | C104: LABEL IMPRIME | D104: 0.1
A105: EREG036 | B105: ETIQUETTE REG036 | C105: LABEL IMPRIME | D105: 0.1
A106: EREGV006 | B106: ETIQUETTE REGV006 | C106: LABEL IMPRIME | D106: 0.04
A107: ELAI045 | B107: ETIQUETTE LAI045 | C107: LABEL IMPRIME
A108: SKIDE034 | B108: ECHANTILLON GELEE LAVANTE | C108: EPAC | D108: 0.02
A109: SKIDE038 | B109: ECHANTILLON CREME DES BEBES | C109: EPAC | D109: 0.02
A110: SKIDE039 | B110: ECHANTILLON POMMADE MAGIQUE | C110: EPAC | D110: 0.02
A111: SKIDE040 | B111: ECHANTILLON LINIMENT | C111: EPAC | D111: 0.02
A112: SHYDE042 | B112: ECHANTILLON GELÉE FLORALE | C112: EPAC | D112: 0.02
A113: SSOL046 | B113: ECHANTILLON FLUIDE SOLAIRE SPF 30 | C113: EPAC | D113: 0.02 | F113: PP
A114: SSOL047 | B114: ECHANTILLON FLUIDE SOLAIRE SPF 50 | C114: EPAC | D114: 0.02 | F114: PP
A115: SLAI045 | B115: ECHANTILLON LAIT RICHE COCO | C115: EPAC | D115: 0.02 | F115: PE
A116: SGOM048 | B116: ECHANTILLON GOMMAGE NOURRISSANT | C116: EPAC | D116: 0.02 | F116: PP
A117: SANO001B | B117: ECHANTILLON MASQUE EXFOLIANT AUX ACIDES DE FRUITS REFORMULATION | C117: EPAC | F117: PE
A118: POT100 | B118: POT EN VERRE 120 ML | C118: POHLI | D118: 0.39
A119: TUBAAEE008 | B119: TUBE CREME DE NUIT AUX ACTIFS OXYGENANTS 5ml | C119: ALBEA | D119: 0.143
A120: TUBAAEE032 | B120: TUBE MASQUE ROSE LACTE APAISANT 5ml | C120: ALBEA | D120: 0.143
A121: TUBAAEV008 | B121: TUBE CREME DE NUIT AUX ACTIFS OXYGENANTS 20ml | C121: TUBE PLANT | D121: 0.143
A122: TUBAAEV032 | B122: TUBE MASQUE ROSE LACTE APAISANT 20ml | C122: TUBE PLANT | D122: 0.143
A123: TUBANOE001 | B123: TUBE MASQUE EXFOLIANT AUX ACIDES DE FRUITS 5ml | C123: ALBEA | D123: 0.143
A124: TUBANOE004 | B124: TUBE CREME REVEIL MULTIVITAMINEE 5ml | C124: ALBEA | D124: 0.143
A125: TUBANOV001 | B125: TUBE MASQUE AUX ACIDES DE FRUITS 20ml | C125: TUBE PLANT | D125: 0.143
A126: TUBANOV001B | B126: TUBE MASQUE AUX ACIDES DE FRUITS REFORMULATION 20ml | C126: TUBE PLANT
A127: TUBANOV004 | B127: TUBE CREME REVEIL MULTIVITAMINEE 20ml | C127: TUBE PLANT | D127: 0.143
A128: TUBHYDE022 | B128: TUBE CREME UNIVERSELLE 5ml | C128: ALBEA | D128: 0.143
A129: TUBHYDE025 | B129: TUBE LAIT DOUCEUR VANILLE NETTOYANT 5ml | C129: ALBEA | D129: 0.143
A130: TUBHYDV022 | B130: TUBE CREME UNIVERSELLE 20ml | C130: TUBE PLANT | D130: 0.143
A131: TUBHYDV025 | B131: TUBE LAIT DOUCEUR VANILLE NETTOYANT 50ml | C131: TUBE PLANT | D131: 0.171
A132: TUBHYDV042 | B132: TUBE GELÉE FLORALE ULTRA HYDRATANTE 20ml | C132: TUBE PLANT | D132: 0.143
A133: TUBKID039 | B133: TUBE POMMADE MAGIQUE 30ml | C133: TUBE PLANT | D133: 0.2
A134: TUBKIDV038 | B134: TUBE CREME DES BEBES 20ml | C134: TUBE PLANT | D134: 0.2
A135: TUBPURE016 | B135: TUBE GELEE NOIRE NETTOYANTE AUX ACTIFS PURIFIANTS 5ml | C135: ALBEA | D135: 0.143 | E135: Flacon verre | F135: Fabriqué en Europe
A136: TUBPURE023 | B136: TUBE FLUIDE PEAU PARFAITE 5ml | C136: ALBEA | D136: 0.143 | E136: Flacon verre | F136: Fabriqué en Europe
A137: TUBPURV016 | B137: TUBE GELEE NOIRE NETTOYANTE AUX ACTIFS PURIFIANTS 50ml | C137: TUBE PLANT | D137: 0.171 | E137: Pot verre | F137: Fabriqué en Europe
A138: TUBPURV023 | B138: TUBE FLUIDE PEAU PARFAITE 20ml | C138: TUBE PLANT | D138: 0.143 | E138: Pot verre | F138: Fabriqué en Europe
A139: TUBREGE005 | B139: TUBE CREME CONCENTREE AUX ACTIFS REPULPANTS 5ml | C139: ALBEA | D139: 0.143 | E139: Pompe | F139: Fabriqué en Europe
A140: TUBREGV005 | B140: TUBE CREME CONCENTREE AUX ACTIFS REPULPANTS 20ml | C140: TUBE PLANT | D140: 0.143 | E140: Capot | F140: Fabriqué en Europe
A141: TUBSOL046 | B141: TUBE FLUIDE SOLAIRE SPF 30 100ml | C141: TUBE PLANT | E141: Flip top | F141: Fabriqué en Europe
...

Sheet Allergènes 81
A2: % de la substance allergène dans la matière première | F2: Allergènes | G2: Benzyl alcohol | H2: 6-Methylcoumarin | I2: Citral | J2: Geranial | K2: Neral | L2: Isoeugenol | M2: Isoeugenol | N2: Isoeugenol | O2: Citronellol | P2: Citronellol | Q2: Citronellol | R2: Citronellol | S2: Limonene | T2: Limonene | U2: Limonene | V2: Limonene | W2: Pinus Mugo Leaf Oil Pinus Mugo Twig Leaf Extract Pinus Mugo Twig Oil | X2: Pinus Pumila needle extract Pinus Pumila Twig Leaf Extract Pinus Pumila Twig Leaf Oil | Y2: Cedrus Atlantica Bark Extract Cedrus Atlantica Bark Oil Cedrus Atlantica Bark Water Cedrus Atlantica Leaf Extract Cedrus Atlantica Wood Extract Cedrus Atlantica Wood Oil | Z2: Cedrus Atlantica Bark Extract Cedrus Atlantica Bark Oil Cedrus Atlantica Bark Water Cedrus Atlantica Leaf Extract Cedrus Atlantica Wood Extract Cedrus Atlantica Wood Oil | AA2: Turpentine | AB2: Turpentine | AC2: Turpentine | AD2: Alpha-terpinene | AE2: Terpinolene | AF2: Myroxylon Balsamum Pereirae Balsam Extract; Myroxylon Balsamum Pereirae Balsam Oil; Myroxylon Pereirae Oil; Myroxylon Pereirae Resin Extract; Myroxylon Pereirae Resin | AG2: Aalpha-Damascone; cis-Rose ketone 1 cis Rose ketone 2 (cis-beta-Damascone) trans-Rose ketone 2 (trans-beta-Damascone) | AH2: Aalpha-Damascone; cis-Rose ketone 1 | AI2: trans-Rose ketone 1 | AJ2: Rose ketone 4 (Damascenone) | AK2: Rose ketone 3 (delta-Damascone) | AL2: trans-Rose ketone 3 | AM2: cis Rose ketone 2 (cis-beta-Damascone) | AN2: trans-Rose ketone 2 (trans-beta-Damascone) | AO2: 3-Propylidenephthalide | AP2: Lippia citriodora absolute | AQ2: Lippia citriodora absolute | AR2: Acetyl Cedrene | AS2: Amyl Salicylate | AT2: Anethole | AU2: Anethole | AV2: Benzaldehyde | AW2: Camphor | AX2: Camphor | AY2: Camphor | AZ2: Camphor | BA2: Beta-Caryophyllene | BB2: Carvone | BC2: Carvone | BD2: Carvone | BE2: Dimethyl phenethyl Acetate | BF2: Hexadecanolactone | BG2: Hexamethylindanopyran | BH2: Linalyl Acetate | BI2: Menthol | BJ2: Menthol | BK2: Menthol | BL2: Menthol | BM2: Methyl Salicylate | BN2: Ebanol | BO2: Salicylaldehyde | BP2: Santalol | BQ2: Santalol | BR2: Santalol | BS2: Sclareol | BT2: Terpineol | BU2: Alpha Terpineol | BV2: Terpineol | BW2: Terpineol | BX2: Tetramethyl acetyloctahydronaphthalenes | BY2: Tetramethyl acetyloctahydronaphthalenes | BZ2: Tetramethyl acetyloctahydronaphthalenes | CA2: Tetramethyl acetyloctahydronaphthalenes | CB2: Trimethylbenzenepropanol | CC2: Vanillin | CD2: Cananga Odorata Flower Extract | CE2: Cananga Odorata Flower Extract | CF2: Cananga Odorata Flower Oil | CG2: Cananga Odorata Flower Oil | CH2: Cinnamomum Cassia Leaf Oil | CI2: Cinnamomum Cassia Leaf Oil | CJ2: Cinnamomum Zeylanicum Bark Oil | CK2: Cinnamomum Zeylanicum Bark Oil | CL2: Citrus Aurantium Amara Flower Oil | CM2: Citrus Aurantium Dulcis Flower Oil | CN2: Citrus Aurantium Dulcis Flower Oil | CO2: Citrus Aurantium Amara Peel Oil Citrus Sinensis Peel Oil | CP2: Citrus Aurantium Amara Peel Oil | CQ2: Citrus Sinensis Peel Oil | CR2: Citrus Aurantium Dulcis Peel Oil; Citrus Sinensis Peel Oil | CS2: Citrus Aurantium Dulcis Peel Oil; Citrus Sinensis Peel Oil | CT2: Citrus Aurantium Bergamia Peel Oil | CU2: Citrus Aurantium Bergamia Peel Oil | CV2: Citrus Aurantium Bergamia Peel Oil | CW2: Citrus Aurantium Bergamia Peel Oil | CX2: Citrus Aurantium Bergamia Peel Oil | CY2: Citrus Limon Peel Oil | CZ2: Citrus Limon Peel Oil | DA2: Cymbopogon Schoenantus Oil | DB2: Cymbopogon Schoenantus Oil | DC2: Cymbopogon Citratus Leaf Oil Cymbopogon Flexuosus Oil | DD2: Eucalyptus Globulus Leaf Oil Eucalyptus Globulus Leaf/Twig Oil | DE2: Eucalyptus Globulus Leaf Oil Eucalyptus Globulus Leaf/Twig Oil | DF2: Eugenia Caryophyllus Leaf Oil Eugenia Caryophyllus Flower Oil Eugenia Caryophyllus Stem Oil Eugenia Caryophyllus Bud Oil | DG2: Eugenia Caryophyllus Leaf Oil Eugenia Caryophyllus Flower Oil Eugenia Caryophyllus Stem Oil Eugenia Caryophyllus Bud Oil | DH2: Eugenia Caryophyllus Leaf Oil Eugenia Caryophyllus Flower Oil Eugenia Caryophyllus Stem Oil Eugenia Caryophyllus Bud Oil | DI2: Jasminum Grandiflorum Flower Extract; Jasminum Officinale Oil Jasminum Officinale Flower Extract; | DJ2: Jasminum Grandiflorum Flower Extract; Jasminum Officinale Oil Jasminum Officinale Flower Extract; | DK2: Jasminum Grandiflorum Flower Extract; Jasminum Officinale Oil Jasminum Officinale Flower Extract; | DL2: Jasminum Grandiflorum Flower Extract; Jasminum Officinale Oil Jasminum Officinale Flower Extract; | DM2: Jasminum Grandiflorum Flower Extract; Jasminum Officinale Oil Jasminum Officinale Flower Extract; | DN2: Juniperus Virginiana Oil; Juniperus Virginiana Wood Oil | DO2: Laurus Nobilis Leaf Oil | DP2: Laurus Nobilis Leaf Oil | DQ2: Laurus Nobilis Leaf Oil | DR2: Lavandula Hybrida Oil; Lavandula Hybrida Extract; Lavandula Hybrida Flower Extract; | DS2: Lavandula Hybrida Oil; Lavandula Hybrida Extract; Lavandula Hybrida Flower Extract; | DT2: Lavandula Hybrida Oil; Lavandula Hybrida Extract; Lavandula Hybrida Flower Extract; | DU2: Lavandula Hybrida Oil; Lavandula Hybrida Extract; Lavandula Hybrida Flower Extract; | DV2: Lavandula Hybrida Oil; Lavandula Hybrida Extract; Lavandula Hybrida Flower Extract; | DW2: Lavandula Intermedia Flower/Leaf/Stem Extract; Lavandula Intermedia Flower/Leaf/Stem Oil; Lavandula intermedia Oil Lavendula Angustifolia Oil; Lavendula Angustifolia Flower/Leaf/Stem Extract | DX2: Lavandula Intermedia Flower/Leaf/Stem Extract; Lavandula Intermedia Flower/Leaf/Stem Oil; Lavandula intermedia Oil Lavendula Angustifolia Oil; Lavendula Angustifolia Flower/Leaf/Stem Extract | DY2: Mentha Piperita Oil | DZ2: Mentha Piperita Oil | EA2: Mentha Viridis Leaf Oil | EB2: Mentha Viridis Leaf Oil | EC2: Narcissus Poeticus Extract Narcissus Pseudonarcissus Flower Extract Narcissus Jonquilla Extract Narcissus Tazetta Extract | ED2: Narcissus Poeticus Extract Narcissus Pseudonarcissus Flower Extract Narcissus Jonquilla Extract Narcissus Tazetta Extract | EE2: Narcissus Poeticus Extract Narcissus Pseudonarcissus Flower Extract Narcissus Jonquilla Extract Narcissus Tazetta Extract | EF2: Narcissus Poeticus Extract Narcissus Pseudonarcissus Flower Extract Narcissus Jonquilla Extract Narcissus Tazetta Extract | EG2: Pelargonium Graveolens Flower Oil | EH2: Pelargonium Graveolens Flower Oil | EI2: Pogostemon Cablin Oil | EJ2: Pogostemon Cablin Oil | EK2: Rosa Damascena Flower Oil; Rosa Damascena Flower Extract Rosa Alba Flower Oil; Rosa Alba Flower Extract Rosa Canina Fruit Oil Rosa Centifolia Flower Oil; Rosa Centifolia Flower Extract Rosa Gallica Flower Oil Rosa Moschata Flower Oil Rosa Rugosa Flower Oil | EL2: Rosa Damascena Flower Oil; Rosa Damascena Flower Extract Rosa Alba Flower Oil; Rosa Alba Flower Extract Rosa Canina Fruit Oil Rosa Centifolia Flower Oil; Rosa Centifolia Flower Extract Rosa Gallica Flower Oil Rosa Moschata Flower Oil Rosa Rugosa Flower Oil | EM2: Rosa Damascena Flower Oil; Rosa Damascena Flower Extract Rosa Alba Flower Oil; Rosa Alba Flower Extract Rosa Canina Fruit Oil Rosa Centifolia Flower Oil; Rosa Centifolia Flower Extract Rosa Gallica Flower Oil Rosa Moschata Flower Oil Rosa Rugosa Flower Oil | EN2: Rosa Damascena Flower Oil; Rosa Damascena Flower Extract Rosa Alba Flower Oil; Rosa Alba Flower Extract Rosa Canina Fruit Oil Rosa Centifolia Flower Oil; Rosa Centifolia Flower Extract Rosa Gallica Flower Oil Rosa Moschata Flower Oil Rosa Rugosa Flower Oil | EO2: Rosa Damascena Flower Oil; Rosa Damascena Flower Extract Rosa Alba Flower Oil; Rosa Alba Flower Extract Rosa Canina Fruit Oil Rosa Centifolia Flower Oil; Rosa Centifolia Flower Extract Rosa Gallica Flower Oil Rosa Moschata Flower Oil Rosa Rugosa Flower Oil | EP2: Rosa Damascena Flower Oil; Rosa Damascena Flower Extract Rosa Alba Flower Oil; Rosa Alba Flower Extract Rosa Canina Fruit Oil Rosa Centifolia Flower Oil; Rosa Centifolia Flower Extract Rosa Gallica Flower Oil Rosa Moschata Flower Oil Rosa Rugosa Flower Oil | EQ2: Rosa Damascena Flower Oil; Rosa Damascena Flower Extract Rosa Alba Flower Oil; Rosa Alba Flower Extract Rosa Canina Fruit Oil Rosa Centifolia Flower Oil; Rosa Centifolia Flower Extract Rosa Gallica Flower Oil Rosa Moschata Flower Oil Rosa Rugosa Flower Oil | ER2: Santalum Album Oil | ES2: Santalum Album Oil | ET2: Eugenyl Acetate | EU2: Geranyl Acetate | EV2: Isoeugenyl Acetate | EW2: Pinene | EX2: Pinene | EY2: Pinene | EZ2: Pinene | FA2: Cinnamyl alcohol | FB2: Eugenol | FC2: Hydroxycitronellal | FD2: Amyl cinnamal | FE2: Amylcinnamyl alcohol | FF2: Benzyl salicylate | FG2: Cinnamal | FH2: Coumarin | FI2: Geraniol | FJ2: Anise alcohol | FK2: Benzyl cinnamate | FL2: Farnesol | FM2: Linalool | FN2: Benzyl benzoate | FO2: Hexyl cinnamal | FP2: Methyl 2-octynoate | FQ2: Alpha isomethyl ionone
A3: Code MP | B3: Description | C3: INCI | D3: Nom commercial | E3: Fournisseur | F3: N°CAS | G3: 100-51-6 | H3: 92-48-8 | I3: 5392-40-5 | J3: 141-27-5 | K3: 106-26-3 | L3: 97-54-1 | M3: 5932-68-3 | N3: 5912-86-7 | O3: 106-22-9 | P3: 26489-01-0 | Q3: 1117-61-9 | R3: 7540-51-4 | S3: 138-86-3 | T3: 7705-14-8 | U3: 5989-27-5 | V3: 5989-54-8 | W3: 90082-72-7 | X3: 97676-05-6 | Y3: 92201-55-3 | Z3: 8023-85-6 | AA3: 9005-90-7 | AB3: 8006-64-2 | AC3: 8052-14-0 | AD3: 99-86-5 | AE3: 586-62-9 | AF3: 8007-00-9 | AG3: 43052-87-5 | AH3: 23726-94-5 | AI3: 24720-09-0 | AJ3: 23696-85-7 | AK3: 57378-68-4 | AL3: 71048-82-3 | AM3: 23726-92-3 | AN3: 23726-91-2 | AO3: 17369-59-4 | AP3: 8024-12-2 | AQ3: 85116-63-8 | AR3: 32388-55-9 | AS3: 2050-08-0 | AT3: 104-46-1 | AU3: 4180-23-8 | AV3: 100-52-7 | AW3: 76-22-2 | AX3: 21368-68-3 | AY3: 464-49-3 | AZ3: 464-48-2 | BA3: 87-44-5 | BB3: 99-49-0 | BC3: 6485-40-1 | BD3: 2244-16-8 | BE3: 151-05-3 | BF3: 109-29-5 | BG3: 1222-05-5 | BH3: 115-95-7 | BI3: 89-78-1 | BJ3: 1490-04-6 | BK3: 2216-51-5 | BL3: 15356-60-2 | BM3: 119-36-8 | BN3: 67801-20-1 | BO3: 90-02-8 | BP3: 11031-45-1 | BQ3: 115-71-9 | BR3: 77-42-9 | BS3: 515-03-7 | BT3: 8000-41-7 | BU3: 98-55-5 | BV3: 138-87-4 | BW3: 586-81-2 | BX3: 54464-57-2 | BY3: 54464-59-4 | BZ3: 68155-66-8 | CA3: 68155-67-9 | CB3: 103694-68-4 | CC3: 121-33-5 | CD3: 83863-30-3 | CE3: 8006-81-3 | CF3: 68606-83-7 | CG3: 93686-30-7 | CH3: 8007-80-5 | CI3: 84961-46-6 | CJ3: 8015-91-6 | CK3: 84649-98-9 | CL3: 72968-50-4 | CM3: 8028-48-6 | CN3: 8016-38-4 | CO3: 68916-04-1 | CP3: 72968-50-4 | CQ3: 97766-30-8 | CR3: 8028-48-6 | CS3: 8008-57-9 | CT3: 8007-75-8 | CU3: 89957-91-5 | CV3: 68648-33-9 | CW3: 8007-75-8 | CX3: 85049-52-1 | CY3: 84929-31-7 | CZ3: 8008-56-8 | DA3: 8007-02-1 | DB3: 89998-16-3 | DC3: 91844-92-7 | DD3: 97926-40-4 | DE3: 8000-48-4 | DF3: 8000-34-8 | DG3: 84961-50-2 | DH3: 8015-97-2 | DI3: 84776-64-7 | DJ3: 90045-94-6 | DK3: 8022-96-6 | DL3: 8024-43-9 | DM3: 90045-94-6 | DN3: 8000-27-9/ 85085-41-2 | DO3: 8002-41-3 | DP3: 8007-48-5 | DQ3: 84603-73-6 | DR3: 91722-69-9 | DS3: 8022-15-9 | DT3: 93455-96-0 | DU3: 93455-97-1 | DV3: 92623-76-2 | DW3: 8000-28-0 | DX3: 90063-37-9 | DY3: 8006-90-4 | DZ3: 84082-70-2 | EA3: 8008-79-5 | EB3: 84696-51-5 | EC3: 90064-26-9 | ED3: 68917-12-4 | EE3: 90064-27-0 | EF3: 90064-25-8 | EG3: 90082-51-2 | EH3: 8000-46-2 | EI3: 8014-09-3 | EJ3: 84238-39-1 | EK3: 8007-01-0 | EL3: 90106-38-0 | EM3: 93334-48-6 | EN3: 84696-47-9 | EO3: 84604-12-6 | EP3: 84604-13-7 | EQ3: 92347-25-6 | ER3: 8006-87-9 | ES3: 84787-70-2 | ET3: 93-28-7 | EU3: 105-87-3 | EV3: 93-29-8 | EW3: 80-56-8 | EX3: 7785-70-8 | EY3: 127-91-3 | EZ3: 18172-67-3 | FA3: 104-54-1 | FB3: 97-53-0 | FC3: 107-75-5 | FD3: 122-40-7 | FE3: 101-85-9 | FF3: 118-58-1 | FG3: 104-55-2 | FH3: 91-64-5 | FI3: 106-24-1 | FJ3: 105-13-5 | FK3: 103-41-3 | FL3: 4602-84-0 | FM3: 78-70-6 | FN3: 120-51-4 | FO3: 101-86-0 | FP3: 111-12-6 | FQ3: 127-51-5
F4: Groupement de nom | I4: Citral | J4: Citral | K4: Citral | W4: Pinus Mugo | X4: Pinus Pumila | Y4: Cedrus Atlantica | Z4: Cedrus Atlantica | AF4: Myroxylon Pereirae Oil/Extract | AG4: Rose Ketones | AH4: Rose Ketones | AI4: Rose Ketones | AJ4: Rose Ketones | AK4: Rose Ketones | AL4: Rose Ketones | AM4: Rose Ketones | AN4: Rose Ketones | CD4: Cananga Odorata Oil/Extract | CE4: Cananga Odorata Oil/Extract | CF4: Cananga Odorata Oil/Extract | CG4: Cananga Odorata Oil/Extract | CL4: Citrus Aurantium Flower Oil | CM4: Citrus Aurantium Flower Oil | CN4: Citrus Aurantium Flower Oil | CO4: Citrus Aurantium Peel oil | CP4: Citrus Aurantium Peel oil | CQ4: Citrus Aurantium Peel oil | CR4: Citrus Aurantium Peel oil | CS4: Citrus Aurantium Peel oil | DA4: Lemongrass Oil | DB4: Lemongrass Oil | DC4: Lemongrass Oil | DD4: Eucalyptus Globulus Oil | DE4: Eucalyptus Globulus Oil | DF4: Eugenia Caryophyllus Oil | DG4: Eugenia Caryophyllus Oil | DH4: Eugenia Caryophyllus Oil | DI4: Jasmine Oil/Extract | DJ4: Jasmine Oil/Extract | DK4: Jasmine Oil/Extract | DL4: Jasmine Oil/Extract | DM4: Jasmine Oil/Extract | DN4: Juniperus Virginiana Oil | DR4: Lavandula Oil/Extract | DS4: Lavandula Oil/Extract | DT4: Lavandula Oil/Extract | DU4: Lavandula Oil/Extract | DV4: Lavandula Oil/Extract | DW4: Lavandula Oil/Extract | DX4: Lavandula Oil/Extract | EC4: Narcissus Extract | ED4: Narcissus Extract | EE4: Narcissus Extract | EF4: Narcissus Extract | EG4: Pelargonium Graveolens Flower Oil | EH4: Pelargonium Graveolens Flower Oil | EK4: Rose Flower Oil/Extract | EL4: Rose Flower Oil/Extract | EM4: Rose Flower Oil/Extract | EN4: Rose Flower Oil/Extract | EO4: Rose Flower Oil/Extract | EP4: Rose Flower Oil/Extract | EQ4: Rose Flower Oil/Extract
A5: 1 | B5: 2 | C5: 3 | D5: 4 | E5: 5 | F5: 6 | G5: 7 | H5: 8 | I5: 9 | J5: 10 | K5: 11 | L5: 12 | M5: 13 | N5: 14 | O5: 15 | P5: 16 | Q5: 17 | R5: 18 | S5: 19 | T5: 20 | U5: 21 | V5: 22 | W5: 23 | X5: 24 | Y5: 25 | Z5: 26 | AA5: 27 | AB5: 28 | AC5: 29 | AD5: 30 | AE5: 31 | AF5: 32 | AG5: 33 | AH5: 34 | AI5: 35 | AJ5: 36 | AK5: 37 | AL5: 38 | AM5: 39 | AN5: 40 | AO5: 41 | AP5: 42 | AQ5: 43 | AR5: 44 | AS5: 45 | AT5: 46 | AU5: 47 | AV5: 48 | AW5: 49 | AX5: 50 | AY5: 51 | AZ5: 52 | BA5: 53 | BB5: 54 | BC5: 55 | BD5: 56 | BE5: 57 | BF5: 58 | BG5: 59 | BH5: 60 | BI5: 61 | BJ5: 62 | BK5: 63 | BL5: 64 | BM5: 65 | BN5: 66 | BO5: 67 | BP5: 68 | BQ5: 69 | BR5: 70 | BS5: 71 | BT5: 72 | BU5: 73 | BV5: 74 | BW5: 75 | BX5: 76 | BY5: 77 | BZ5: 78 | CA5: 79 | CB5: 80 | CC5: 81 | CD5: 82 | CE5: 83 | CF5: 84 | CG5: 85 | CH5: 86 | CI5: 87 | CJ5: 88 | CK5: 89 | CL5: 90 | CM5: 91 | CN5: 92 | CO5: 93 | CP5: 94 | CQ5: 95 | CR5: 96 | CS5: 97 | CT5: 98 | CU5: 99 | CV5: 100 | CW5: 101 | CX5: 102 | CY5: 103 | CZ5: 104 | DA5: 105 | DB5: 106 | DC5: 107 | DD5: 108 | DE5: 109 | DF5: 110 | DG5: 111 | DH5: 112 | DI5: 113 | DJ5: 114 | DK5: 115 | DL5: 116 | DM5: 117 | DN5: 118 | DO5: 119 | DP5: 120 | DQ5: 121 | DR5: 122 | DS5: 123 | DT5: 124 | DU5: 125 | DV5: 126 | DW5: 127 | DX5: 128 | DY5: 129 | DZ5: 130 | EA5: 131 | EB5: 132 | EC5: 133 | ED5: 134 | EE5: 135 | EF5: 136 | EG5: 137 | EH5: 138 | EI5: 139 | EJ5: 140 | EK5: 141 | EL5: 142 | EM5: 143 | EN5: 144 | EO5: 145 | EP5: 146 | EQ5: 147 | ER5: 148 | ES5: 149 | ET5: 150 | EU5: 151 | EV5: 152 | EW5: 153 | EX5: 154 | EY5: 155 | EZ5: 156 | FA5: 157 | FB5: 158 | FC5: 159 | FD5: 160 | FE5: 161 | FF5: 162 | FG5: 163 | FH5: 164 | FI5: 165 | FJ5: 166 | FK5: 167 | FL5: 168 | FM5: 169 | FN5: 170 | FO5: 171 | FP5: 172 | FQ5: 173
A6: MP501B | B6: He d'ylang ylang complète BIO | C6: CANANGA ODORATA FLOWER OIL | D6: YLANG COMPLETE HE BIO | E6: Diffusions aromatiques | G6: 0 | H6: 1 | I6: 0
A7: MP502 | B7: He Vetiver Haïti BIO | C7: VETIVERIA ZIZANOIDES ROOT OIL | D7: VETYVER HAITI HUILE ESSENTIELLE | E7: Astier Demarest | M7: 0.06 | S7: 0.004 | BA7: 0.015 | EW7: 0.034 | EY7: 0.004
A8: MP503B | B8: He Tea tree BIO | C8: MELALEUCA ALTERNIFOLIA LEAF OIL | D8: TEA TREE HUILE ESSENTIELLE BIO | E8: Diffusions aromatiques | S8: 2 | AD8: 10 | AE8: 4 | AW8: 0.01 | BA8: 1 | BT8: 4 | EW8: 5 | FI8: 0.1 | FM8: 1
A9: MP504 | B9: He Shiu 98% | C9: CINNAMOMUM CAMPHORA LEAF OIL | D9: HO WOOD HE | E9: Diffusions aromatiques
A10: MP505B | B10: He Petit grain BIO | C10: CITRUS AURANTIUM LEAF OIL | D10: PETITGRAIN PARAGUAY HE BIO | E10: Diffusions aromatiques | I10: 0.7 | O10: 0.05 | S10: 3.5 | AD10: 0.1 | BA10: 1.5 | BB10: 0.01 | BM10: 0.01 | BT10: 7 | EW10: 2.3 | FF10: 0.1 | FI10: 4.5 | FL10: 0.01 | FM10: 30
A11: MP506B | B11: He Palmarosa BIO | C11: CYMBOPOGON MARTINI OIL | D11: PALMAROSA HE BIO Cymbopogon Martinii Bio | E11: Diffusions aromatiques
A12: MP507B | B12: He Orange sanguine | C12: CITRUS AURANTIUM DULCIS PEEL OIL | D12: ORANGE SANGUINE HUILE ESSENTIELLE | E12: Diffusions aromatiques | I12: 0.15 | S12: 96 | BT12: 0.05 | CS12: 100 | EW12: 0.75 | FM12: 0.2
A13: MP508B | B13: He Lavande fine BIO | C13: LAVANDULA ANGUSTIFOLIA OIL | D13: LAVANDE TRADITIONELLE FRANCE HE BIO | E13: Diffusions aromatiques | S13: 0.5 | AW13: 0.5 | BA13: 5.7 | BH13: 45 | BT13: 2 | DW13: 100 | EU13: 0.8 | EW13: 0.8 | FH13: 0.2 | FI13: 2 | FM13: 40
A14: MP510B | B14: He Géranium Rosat BIO | C14: PELARGONIUM GRAVEOLENS STEM LEAF OIL | D14: GERANIUM EGYPTE HE BIO | E14: Diffusions aromatiques | G14: 0.0075 | I14: 2 | O14: 39 | S14: 0.25 | AD14: 0.99 | EH14: 100 | FF14: 0.0065 | FI14: 20 | FM14: 8 | FN14: 0.0075
A15: MP511B | B15: He Citron incolore sans furocoumarine BIO | C15: Citrus Lemon Peel Oil | D15: CITRON RECTIFIE SANS FUROCOUMARINE WW / SB | E15: Diffusions aromatiques | S15: 70 | AD15: 0.2 | AE15: 0.3 | BA15: 0.3 | BT15: 0.2 | CY15: 100 | EU15: 0.2 | EW15: 16 | FI15: 0.04 | FM15: 0.2
A16: MP513B | B16: He Bergamotte incolore sans furocoumarine BIO | C16: CITRUS AURANTIUM BERGAMIA FRUIT OIL | D16: BERGAMOTE FCF HE ITALIE BIO | E16: Diffusions aromatiques | I16: 0.6 | S16: 45 | AD16: 0.2 | AE16: 0.35 | BA16: 0.3 | BT16: 0.2 | CT16: 100 | EU16: 0.35 | EW16: 11 | FI16: 0.04 | FM16: 15
A17: MP514 | B17: HE Baie Rose | C17: SCHINUS TEREBENTHIFOLIUS FRUIT OIL | D17: BAIES ROSES HE (schinus terebenthifolius) | E17: Diffusions aromatiques
A18: MP515B | B18: He Romarin Bio | C18: ROSMARINUS OFFICINALIS LEAF OIL | D18: ROMARIN CINEOL HUILE ESSENTIELLE BIO | E18: Diffusions aromatiques | S18: 5 | AD18: 0.4 | AW18: 10 | BA18: 3 | BT18: 2 | EW18: 24 | FM18: 0.75
A19: MP516B | B19: He Litsea Cubeba BIO | C19: LITSEA CUBEBA FRUIT OIL | D19: LITSEA CUBEBA HE BIO | E19: Diffusions aromatiques
A20: MP517 | B20: He Eucalyptus globulus | C20: EUCALYPTUS GLOBULUS LEAF OIL | D20: EUCALYPTUS GLOBULUS HE 80/85% | E20: Diffusions aromatiques
A21: MP519 | B21: He amande amère | C21: PRUNUS ARMENIACA KERNEL OIL | D21: AMANDE AMERE HE | E21: Diffusions aromatiques | G21: 1 | AV21: 99
A22: MP524 | B22: HE rose de Damas LM | C22: ROSA DAMASCENA FLOWER OIL | D22: ROSE HUILE ESSENTIELLE LOW METHYL EUGENOL | E22: Diffusions aromatiques | G22: 0.04 | I22: 2.5 | O22: 43 | S22: 0.1 | AD22: 0.05 | AG22: 0.1 | AV22: 0.12 | BA22: 0.5 | BM22: 0.05 | EU22: 3 | EW22: 5.5 | FB22: 0.3 | FF22: 0.01 | FI22: 25 | FL22: 2.4 | FM22: 2 | FN22: 0.15
A23: MP550 | B23: Fragrance Vanille TK 60669 | C23: Fragrance | D23: VANILLE TK 60669 | E23: Argeville
A24: MP551 | B24: Fruit de la passion NAT CO 60645 | C24: Fragrance | D24: FRUIT DE LA PASSION NAT CO 60645 | E24: Argeville | G24: 0.0039 | I24: 0.1326 | O24: 0.0072 | S24: 14.7328 | AD24: 0.0134 | AE24: 0.0199 | AV24: 0.5006 | BA24: 0.0122 | BB24: 0.0103 | BV24: 0.039 | CO24: 12.332 | CY24: 3.2 | EU24: 0.0241 | EW24: 0.8287 | FB24: 0.0015 | FG24: 0.5 | FI24: 0.0222 | FL24: 0.0013 | FM24: 0.0951
A25: MP552 | B25: Fragrance Code VAN Jasmin 3150/4 | C25: Fragrance | D25: C3150/4 | E25: VANESSENCE | G25: 0.0015 | I25: 0.016 | L25: 0.006 | S25: 1.239 | AD25: 0.0025 | AE25: 0.0109 | AU25: 0.0045 | AV25: 0.0015 | BA25: 0.2344 | BH25: 1.95 | BM25: 0.0045 | BU25: 0.187 | CC25: 0.0002 | CE25: 1.5 | CS25: 1 | CT25: 0.5 | EU25: 1.325 | EW25: 0.1037 | FA25: 0.0015 | FB25: 1.0315 | FF25: 0.06 | FG25: 0.0002 | FI25: 5.19 | FK25: 0.0002 | FL25: 0.042 | FM25: 18.76 | FN25: 0.15
A26: MP553 | B26: Fragrance fleur d'oranger | C26: Fragrance | D26: Composition Fleur oranger | E26: Laboratoire Rosier Davenne
A27: MP526 | B27: HE Néroli Tunisie | C27: Citrus Aurantium Flower Oil | D27: HE Néroli Tunisie | E27: Diffusions aromatiques
A28: MP202B | B28: =VLOOKUP(A28,Liste!A1:O1128,2,0) -> Hydrolat Menthe Poivrée BIO | C28: =VLOOKUP(A28,Liste!A1:O969,4,0) -> Mentha Piperita Leaf Water* | D28: =VLOOKUP(A28,Liste!A1:O955,2,0) -> Hydrolat Menthe Poivrée BIO | E28: =VLOOKUP(A28,Liste!A1:O953,3,0) -> Florihana | U28: 0.005 | BI28: 0.00281 | BU28: 0.001 | FM28: 0.005
A29: MP110B | B29: =VLOOKUP(A29,Liste!A2:O1129,2,0) -> Huile vierge de prune bio | C29: =VLOOKUP(A29,Liste!A2:O970,4,0) -> Prunus Domestica Seed Oil | D29: =VLOOKUP(A29,Liste!A2:O956,2,0) -> Huile vierge de prune bio | E29: =VLOOKUP(A29,Liste!A2:O953,3,0) -> Perle de Gascogne | G29: 0.015 | AV29: 0.25 | CC29: 0.003
A30: MP205B | B30: =VLOOKUP(A30,Liste!A3:O1130,2,0) -> Hydrolat de lavande fine sauvage BIO | C30: =VLOOKUP(A30,Liste!A3:O971,4,0) -> Lavandula Angustifolia Flower Water* | D30: =VLOOKUP(A30,Liste!A3:O957,2,0) -> Hydrolat de lavande fine sauvage BIO | E30: =VLOOKUP(A30,Liste!A3:O955,3,0) -> Florihana | U30: 0.001 | FH30: 0.001 | FI30: 0.001 | FM30: 0.025
A31: MP204B | B31: =VLOOKUP(A31,Liste!A4:O1131,2,0) -> Hydrolat de fleur d'oranger (Néroli) BIO non conservé | C31: =VLOOKUP(A31,Liste!A4:O972,4,0) -> Citrus Aurantium Amara Flower Water* | D31: =VLOOKUP(A31,Liste!A4:O958,2,0) -> Hydrolat de fleur d'oranger (Néroli) BIO non conservé | E31: =VLOOKUP(A31,Liste!A4:O956,3,0) -> Florihana | G31: 0.001 | I31: 0.001 | O31: 0.001 | U31: 0.001 | FB31: 0.001 | FI31: 0.005 | FL31: 0.002 | FM31: 0.02
A32: MP114B | B32: =VLOOKUP(A32,Liste!A5:O1132,2,0) -> Macérât de lavande bio | C32: =VLOOKUP(A32,Liste!A5:O973,4,0) -> Olea Europaea Fruit Oil* >99%, Lavandula Angustifolia Flower Extract*<1% | D32: =VLOOKUP(A32,Liste!A5:O959,2,0) -> Macérât de lavande bio | E32: =VLOOKUP(A32,Liste!A5:O957,3,0) -> La Canopée | AW32: 0.00175 | BA32: 0.00598 | BH32: 0.258 | FH32: 0.00141 | FM32: 0.0772
A33: MP200B | B33: =VLOOKUP(A33,Liste!A6:O1133,2,0) -> Hydrolat Rose damas Bio (conservé à 2% leucidal liquid) | C33: =VLOOKUP(A33,Liste!A6:O974,4,0) -> Rosa Damascena Flower Water* 98% 2% Leuconostoc/Radish Root Ferment Filtrate 50% (and) Aqua 50% | D33: =VLOOKUP(A33,Liste!A6:O960,2,0) -> Hydrolat Rose damas Bio (conservé à 2% leucidal liquid) | E33: =VLOOKUP(A33,Liste!A6:O958,3,0) -> Gazignaire | G33: 9e-05 | I33: 9e-05 | O33: 0.002 | BT33: 0.0001 | EK33: 0.012 | EU33: 9e-05 | FB33: 0.0004 | FI33: 0.004 | FM33: 0.0004
A34: ECH-ROS006 | B34: =VLOOKUP(A34,Liste!A7:O1134,2,0) -> Rose HE Bulgarie | C34: =VLOOKUP(A34,Liste!A7:O975,4,0) -> ROSA DAMASCENA FLOWER OIL | D34: =VLOOKUP(A34,Liste!A7:O961,2,0) -> Rose HE Bulgarie | E34: =VLOOKUP(A34,Liste!A7:O959,3,0) -> Atmosphaer | O34: 29.8 | EU34: 1.08 | FB34: 0.98 | FL34: 2 | FM34: 1.06
A35: MP523 | B35: =VLOOKUP(A35,Liste!A8:O1135,2,0) -> Vanilline | C35: =VLOOKUP(A35,Liste!A8:O976,4,0) -> Vanillin | D35: =VLOOKUP(A35,Liste!A8:O962,2,0) -> Vanilline | E35: =VLOOKUP(A35,Liste!A8:O960,3,0) -> Diffusions aromatiques
A36: MP201B | B36: =VLOOKUP(A36,Liste!A9:O1136,2,0) -> Hydrolat Fleur d'Oranger BIO (conservé) | C36: =VLOOKUP(A36,Liste!A9:O977,4,0) -> Citrus Aurantium Amara Flower water 98% Aqua 1% Leuconostoc/Radish Root Ferment Filtrate 1% | D36: =VLOOKUP(A36,Liste!A9:O963,2,0) -> Hydrolat Fleur d'Oranger BIO (conservé) | E36: =VLOOKUP(A36,Liste!A9:O961,3,0) -> Gazignaire | BT36: 0.015 | CL36: 0.03 | EU36: 0.0001 | FI36: 0.0003 | FM36: 0.025

Sheet IFRA
A2: IFRA CATÉGORIES | F2: Catégories | G2: 1 | H2: 2 | I2: 3 | J2: 4 | K2: 5A | L2: 5B | M2: 5D | N2: 6* | O2: 7A | P2: 7B | Q2: 8 | R2: 9 | S2: 10A | T2: 10B | U2: 11A | V2: 11B | W2: 12
F3: Description | G3: Produits appliqués sur les lèvres | H3: Produits appliqués sur les aisselles | I3: Produits appliqués sur le visage/corps du bout des doigts | J3: Produits liés à la Parfumerie fine | K3: Produits de lotion pour le corps appliqués sur le corps à l'aide des mains (paumes), principalement non rincés | L3: Produits hydratants pour le visage appliqués sur le visage à l'aide des mains (paumes). principalement non rincés | M3: Produits de crème pour les mains appliqués sur le mains en utilisant des mains (paumes), principalement non rincés | N3: Produits avec exposition orale et labiale | O3: Produits rincés appliqués sur les cheveux avec un certain contact avec les mains | P3: Produits non rincés appliqués sur les cheveux avec un certain contact avec les mains | Q3: Produits à exposition anogénitale importante | R3: Produits corps et mains, principalement rincés | S3: Produits d'entretien ménager avec contact principalement avec les mains à l'exclusion des produits aérosols et sprays | T3: Produits d'entretien ménager avec contact principalement avec les mains: produits aérosols et sprays | U3: Produits avec contact cutané prévu mais transfert minimal de parfum sur la peau sans exposition aux UV | V3: Produits avec contact cutané prévu mais transfert minimal de parfum sur la peau avec exposition aux UV | W3: Produits non destinés à un contact direct ave la peau
A4: MP501B | B4: He d'ylang ylang complète BIO | C4: CANANGA ODORATA FLOWER OIL | D4: YLANG COMPLETE HE BIO | E4: Diffusions aromatiques | G4: 100.0000% | H4: 55.0000% | I4: 100.0000% | J4: 100.0000% | K4: 60.0000% | L4: 100.0000% | M4: 100.0000% | N4: 100.0000% | O4: 90.0000% | P4: 100.0000% | Q4: 100.0000% | R4: 100.0000% | S4: 90.0000% | T4: 100.0000% | U4: 90.0000% | V4: 100.0000% | W4: 100.0000%
A5: MP502 | B5: He Vetiver Haïti BIO | C5: VETIVERIA ZIZANOIDES ROOT OIL | D5: VETYVER HAITI HUILE ESSENTIELLE | E5: Astier Demarest | M5: 0.06 | S5: 0.004
A6: MP503B | B6: He Tea tree BIO | C6: MELALEUCA ALTERNIFOLIA LEAF OIL | D6: TEA TREE HUILE ESSENTIELLE BIO | E6: Diffusions aromatiques | S6: 2
A7: MP504 | B7: He Shiu 98% | C7: CINNAMOMUM CAMPHORA LEAF OIL | D7: HO WOOD HE | E7: Diffusions aromatiques
A8: MP505B | B8: He Petit grain BIO | C8: CITRUS AURANTIUM LEAF OIL | D8: PETITGRAIN PARAGUAY HE BIO | E8: Diffusions aromatiques | I8: 0.7 | O8: 0.05 | S8: 3.5
A9: MP506B | B9: He Palmarosa BIO | C9: CYMBOPOGON MARTINI OIL | D9: PALMAROSA HE BIO Cymbopogon Martinii Bio | E9: Diffusions aromatiques
A10: MP507B | B10: He Orange sanguine | C10: CITRUS AURANTIUM DULCIS PEEL OIL | D10: ORANGE SANGUINE HUILE ESSENTIELLE | E10: Diffusions aromatiques | I10: 0.15 | S10: 96
A11: MP508B | B11: He Lavande fine BIO | C11: LAVANDULA ANGUSTIFOLIA OIL | D11: LAVANDE TRADITIONELLE FRANCE HE BIO | E11: Diffusions aromatiques | S11: 0.5
A12: MP510B | B12: He Géranium Rosat BIO | C12: PELARGONIUM GRAVEOLENS STEM LEAF OIL | D12: GERANIUM EGYPTE HE BIO | E12: Diffusions aromatiques | G12: 0.0075 | I12: 2 | O12: 39 | S12: 0.25
A13: MP511B | B13: He Citron incolore sans furocoumarine BIO | C13: Citrus Lemon Peel Oil | D13: CITRON RECTIFIE SANS FUROCOUMARINE WW / SB | E13: Diffusions aromatiques | S13: 70
A14: MP513B | B14: He Bergamotte incolore sans furocoumarine BIO | C14: CITRUS AURANTIUM BERGAMIA FRUIT OIL | D14: BERGAMOTE FCF HE ITALIE BIO | E14: Diffusions aromatiques | I14: 0.6 | S14: 45
A15: MP514 | B15: HE Baie Rose | C15: SCHINUS TEREBENTHIFOLIUS FRUIT OIL | D15: BAIES ROSES HE (schinus terebenthifolius) | E15: Diffusions aromatiques
A16: MP515B | B16: He Romarin Bio | C16: ROSMARINUS OFFICINALIS LEAF OIL | D16: ROMARIN CINEOL HUILE ESSENTIELLE BIO | E16: Diffusions aromatiques | S16: 5
A17: MP516B | B17: He Litsea Cubeba BIO | C17: LITSEA CUBEBA FRUIT OIL | D17: LITSEA CUBEBA HE BIO | E17: Diffusions aromatiques
A18: MP517 | B18: He Eucalyptus globulus | C18: EUCALYPTUS GLOBULUS LEAF OIL | D18: EUCALYPTUS GLOBULUS HE 80/85% | E18: Diffusions aromatiques
A19: MP519 | B19: He amande amère | C19: PRUNUS ARMENIACA KERNEL OIL | D19: AMANDE AMERE HE | E19: Diffusions aromatiques | G19: 1
A20: MP524 | B20: HE rose de Damas LM | C20: ROSA DAMASCENA FLOWER OIL | D20: ROSE HUILE ESSENTIELLE LOW METHYL EUGENOL | E20: Diffusions aromatiques | G20: 0.04 | I20: 2.5 | O20: 43 | S20: 0.1
A21: MP550 | B21: Fragrance Vanille TK 60669 | C21: Fragrance | D21: VANILLE TK 60669 | E21: Argeville
A22: MP551 | B22: Fruit de la passion NAT CO 60645 | C22: Fragrance | D22: FRUIT DE LA PASSION NAT CO 60645 | E22: Argeville | G22: 0.0039 | I22: 0.1326 | O22: 0.0072 | S22: 14.7328
A23: MP552 | B23: Fragrance Code VAN Jasmin 3150/4 | C23: Fragrance | D23: C3150/4 | E23: VANESSENCE | G23: 0.0015 | I23: 0.016 | L23: 0.006 | S23: 1.239
A24: MP553 | B24: Fragrance fleur d'oranger | C24: Fragrance | D24: Composition Fleur oranger | E24: Laboratoire Rosier Davenne
A25: MP526 | B25: HE Néroli Tunisie | C25: Citrus Aurantium Flower Oil | D25: HE Néroli Tunisie | E25: Diffusions aromatiques
A26: MP202B | B26: =VLOOKUP(A26,Liste!A1:O1128,2,0) -> Hydrolat Menthe Poivrée BIO | C26: =VLOOKUP(A26,Liste!A1:O969,4,0) -> Mentha Piperita Leaf Water* | D26: =VLOOKUP(A26,Liste!A1:O955,2,0) -> Hydrolat Menthe Poivrée BIO | E26: =VLOOKUP(A26,Liste!A1:O953,3,0) -> Florihana | U26: 0.005
A27: MP110B | B27: =VLOOKUP(A27,Liste!A2:O1129,2,0) -> Huile vierge de prune bio | C27: =VLOOKUP(A27,Liste!A2:O970,4,0) -> Prunus Domestica Seed Oil | D27: =VLOOKUP(A27,Liste!A2:O956,2,0) -> Huile vierge de prune bio | E27: =VLOOKUP(A27,Liste!A2:O953,3,0) -> Perle de Gascogne | G27: 0.015
A28: MP205B | B28: =VLOOKUP(A28,Liste!A3:O1130,2,0) -> Hydrolat de lavande fine sauvage BIO | C28: =VLOOKUP(A28,Liste!A3:O971,4,0) -> Lavandula Angustifolia Flower Water* | D28: =VLOOKUP(A28,Liste!A3:O957,2,0) -> Hydrolat de lavande fine sauvage BIO | E28: =VLOOKUP(A28,Liste!A3:O955,3,0) -> Florihana | U28: 0.001
A29: MP204B | B29: =VLOOKUP(A29,Liste!A4:O1131,2,0) -> Hydrolat de fleur d'oranger (Néroli) BIO non conservé | C29: =VLOOKUP(A29,Liste!A4:O972,4,0) -> Citrus Aurantium Amara Flower Water* | D29: =VLOOKUP(A29,Liste!A4:O958,2,0) -> Hydrolat de fleur d'oranger (Néroli) BIO non conservé | E29: =VLOOKUP(A29,Liste!A4:O956,3,0) -> Florihana | G29: 0.001 | I29: 0.001 | O29: 0.001 | U29: 0.001
A30: MP114B | B30: =VLOOKUP(A30,Liste!A5:O1132,2,0) -> Macérât de lavande bio | C30: =VLOOKUP(A30,Liste!A5:O973,4,0) -> Olea Europaea Fruit Oil* >99%, Lavandula Angustifolia Flower Extract*<1% | D30: =VLOOKUP(A30,Liste!A5:O959,2,0) -> Macérât de lavande bio | E30: =VLOOKUP(A30,Liste!A5:O957,3,0) -> La Canopée
A31: MP200B | B31: =VLOOKUP(A31,Liste!A6:O1133,2,0) -> Hydrolat Rose damas Bio (conservé à 2% leucidal liquid) | C31: =VLOOKUP(A31,Liste!A6:O974,4,0) -> Rosa Damascena Flower Water* 98% 2% Leuconostoc/Radish Root Ferment Filtrate 50% (and) Aqua 50% | D31: =VLOOKUP(A31,Liste!A6:O960,2,0) -> Hydrolat Rose damas Bio (conservé à 2% leucidal liquid) | E31: =VLOOKUP(A31,Liste!A6:O958,3,0) -> Gazignaire | G31: 9e-05 | I31: 9e-05 | O31: 0.002
A32: ECH-ROS006 | B32: =VLOOKUP(A32,Liste!A7:O1134,2,0) -> Rose HE Bulgarie | C32: =VLOOKUP(A32,Liste!A7:O975,4,0) -> ROSA DAMASCENA FLOWER OIL | D32: =VLOOKUP(A32,Liste!A7:O961,2,0) -> Rose HE Bulgarie | E32: =VLOOKUP(A32,Liste!A7:O959,3,0) -> Atmosphaer | O32: 29.8
A33: MP523 | B33: =VLOOKUP(A33,Liste!A8:O1135,2,0) -> Vanilline | C33: =VLOOKUP(A33,Liste!A8:O976,4,0) -> Vanillin | D33: =VLOOKUP(A33,Liste!A8:O962,2,0) -> Vanilline | E33: =VLOOKUP(A33,Liste!A8:O960,3,0) -> Diffusions aromatiques
A34: MP201B | B34: =VLOOKUP(A34,Liste!A9:O1136,2,0) -> Hydrolat Fleur d'Oranger BIO (conservé) | C34: =VLOOKUP(A34,Liste!A9:O977,4,0) -> Citrus Aurantium Amara Flower water 98% Aqua 1% Leuconostoc/Radish Root Ferment Filtrate 1% | D34: =VLOOKUP(A34,Liste!A9:O963,2,0) -> Hydrolat Fleur d'Oranger BIO (conservé) | E34: =VLOOKUP(A34,Liste!A9:O961,3,0) -> Gazignaire

Sheet Test allergènes
D2: Test pour allergènes à déclarer
C4: % de la substance allergène dans la matière première / % of the allergenic substance in the raw material
C5: % de la substance allergène dans le produit fini / % of the allergenic substance in the finished product
F6: Allergènes | G6: Benzyl alcohol | I6: 6-Methylcoumarin | K6: Citral | M6: Geranial | O6: Neral | Q6: Isoeugenol | S6: Isoeugenol | U6: Isoeugenol | W6: Citronellol | Y6: Citronellol | AA6: Citronellol | AC6: Citronellol | AE6: Limonene | AG6: Limonene | AI6: Limonene | AK6: Limonene | AM6: Pinus Mugo Leaf Oil Pinus Mugo Twig Leaf Extract Pinus Mugo Twig Oil | AO6: Pinus Pumila needle extract Pinus Pumila Twig Leaf Extract Pinus Pumila Twig Leaf Oil | AQ6: Cedrus Atlantica Bark Extract Cedrus Atlantica Bark Oil Cedrus Atlantica Bark Water Cedrus Atlantica Leaf Extract Cedrus Atlantica Wood Extract Cedrus Atlantica Wood Oil | AS6: Cedrus Atlantica Bark Extract Cedrus Atlantica Bark Oil Cedrus Atlantica Bark Water Cedrus Atlantica Leaf Extract Cedrus Atlantica Wood Extract Cedrus Atlantica Wood Oil | AU6: Turpentine | AW6: Turpentine | AY6: Turpentine | BA6: Alpha-terpinene | BC6: Terpinolene | BE6: Myroxylon Balsamum Pereirae Balsam Extract; Myroxylon Balsamum Pereirae Balsam Oil; Myroxylon Pereirae Oil; Myroxylon Pereirae Resin Extract; Myroxylon Pereirae Resin | BG6: Aalpha-Damascone; cis-Rose ketone 1 cis Rose ketone 2 (cis-beta-Damascone); trans-Rose ketone 2 (trans-beta-Damascone) | BI6: Aalpha-Damascone; cis-Rose ketone 1 | BK6: trans-Rose ketone 1 | BM6: Rose ketone 4 (Damascenone) | BO6: Rose ketone 3 (delta-Damascone) | BQ6: trans-Rose ketone 3 | BS6: cis Rose ketone 2 (cis-beta-Damascone) | BU6: trans-Rose ketone 2 (trans-beta-Damascone) | BW6: 3-Propylidenephthalide | BY6: Lippia citriodora absolute | CA6: Lippia citriodora absolute | CC6: Acetyl Cedrene | CE6: Amyl Salicylate | CG6: Anethole | CI6: Anethole | CK6: Benzaldehyde | CM6: Camphor | CO6: Camphor | CQ6: Camphor | CS6: Camphor | CU6: Beta-Caryophyllene | CW6: Carvone | CY6: Carvone | DA6: Carvone | DC6: Dimethyl phenethyl Acetate | DE6: Hexadecanolactone | DG6: Hexamethylindanopyran | DI6: Linalyl Acetate | DK6: Menthol | DM6: Menthol | DO6: Menthol | DQ6: Menthol | DS6: Methyl Salicylate | DU6: Ebanol | DW6: Salicylaldehyde | DY6: Santalol | EA6: Santalol | EC6: Santalol | EE6: Sclareol | EG6: Terpineol | EI6: Alpha Terpineol | EK6: Terpineol | EM6: Terpineol | EO6: Tetramethyl acetyloctahydronaphthalenes | EQ6: Tetramethyl acetyloctahydronaphthalenes | ES6: Tetramethyl acetyloctahydronaphthalenes | EU6: Tetramethyl acetyloctahydronaphthalenes | EW6: Trimethylbenzenepropanol | EY6: Vanillin | FA6: Cananga Odorata Flower Extract | FC6: Cananga Odorata Flower Extract | FE6: Cananga Odorata Flower Oil | FG6: Cananga Odorata Flower Oil | FI6: Cinnamomum Cassia Leaf Oil | FK6: Cinnamomum Cassia Leaf Oil | FM6: Cinnamomum Zeylanicum Bark Oil | FO6: Cinnamomum Zeylanicum Bark Oil | FQ6: Citrus Aurantium Amara Flower Oil | FS6: Citrus Aurantium Dulcis Flower Oil | FU6: Citrus Aurantium Dulcis Flower Oil | FW6: Citrus Aurantium Amara Peel Oil Citrus Sinensis Peel Oil | FY6: Citrus Aurantium Amara Peel Oil | GA6: Citrus Sinensis Peel Oil | GC6: Citrus Aurantium Dulcis Peel Oil; Citrus Sinensis Peel Oil | GE6: Citrus Aurantium Dulcis Peel Oil; Citrus Sinensis Peel Oil | GG6: Citrus Aurantium Bergamia Peel Oil | GI6: Citrus Aurantium Bergamia Peel Oil | GK6: Citrus Aurantium Bergamia Peel Oil | GM6: Citrus Aurantium Bergamia Peel Oil | GO6: Citrus Aurantium Bergamia Peel Oil | GQ6: Citrus Limon Peel Oil | GS6: Citrus Limon Peel Oil | GU6: Cymbopogon Schoenantus Oil | GW6: Cymbopogon Schoenantus Oil | GY6: Cymbopogon Citratus Leaf Oil Cymbopogon Flexuosus Oil | HA6: Eucalyptus Globulus Leaf Oil Eucalyptus Globulus Leaf/Twig Oil | HC6: Eucalyptus Globulus Leaf Oil Eucalyptus Globulus Leaf/Twig Oil | HE6: Eugenia Caryophyllus Leaf Oil Eugenia Caryophyllus Flower Oil Eugenia Caryophyllus Stem Oil Eugenia Caryophyllus Bud Oil | HG6: Eugenia Caryophyllus Leaf Oil Eugenia Caryophyllus Flower Oil Eugenia Caryophyllus Stem Oil Eugenia Caryophyllus Bud Oil | HI6: Eugenia Caryophyllus Leaf Oil Eugenia Caryophyllus Flower Oil Eugenia Caryophyllus Stem Oil Eugenia Caryophyllus Bud Oil | HK6: Jasminum Grandiflorum Flower Extract; Jasminum Officinale Oil Jasminum Officinale Flower Extract; | HM6: Jasminum Grandiflorum Flower Extract; Jasminum Officinale Oil Jasminum Officinale Flower Extract; | HO6: Jasminum Grandiflorum Flower Extract; Jasminum Officinale Oil Jasminum Officinale Flower Extract; | HQ6: Jasminum Grandiflorum Flower Extract; Jasminum Officinale Oil Jasminum Officinale Flower Extract; | HS6: Jasminum Grandiflorum Flower Extract; Jasminum Officinale Oil Jasminum Officinale Flower Extract; | HU6: Juniperus Virginiana Oil; Juniperus Virginiana Wood Oil | HW6: Laurus Nobilis Leaf Oil | HY6: Laurus Nobilis Leaf Oil | IA6: Laurus Nobilis Leaf Oil | IC6: Lavandula Hybrida Oil; Lavandula Hybrida Extract; Lavandula Hybrida Flower Extract; | IE6: Lavandula Hybrida Oil; Lavandula Hybrida Extract; Lavandula Hybrida Flower Extract; | IG6: Lavandula Hybrida Oil; Lavandula Hybrida Extract; Lavandula Hybrida Flower Extract; | II6: Lavandula Hybrida Oil; Lavandula Hybrida Extract; Lavandula Hybrida Flower Extract; | IK6: Lavandula Hybrida Oil; Lavandula Hybrida Extract; Lavandula Hybrida Flower Extract; | IM6: Lavandula Intermedia Flower/Leaf/Stem Extract; Lavandula Intermedia Flower/Leaf/Stem Oil; Lavandula intermedia Oil Lavendula Angustifolia Oil; Lavendula Angustifolia Flower/Leaf/Stem Extract | IO6: Lavandula Intermedia Flower/Leaf/Stem Extract; Lavandula Intermedia Flower/Leaf/Stem Oil; Lavandula intermedia Oil Lavendula Angustifolia Oil; Lavendula Angustifolia Flower/Leaf/Stem Extract | IQ6: Mentha Piperita Oil | IS6: Mentha Piperita Oil | IU6: Mentha Viridis Leaf Oil | IW6: Mentha Viridis Leaf Oil | IY6: Narcissus Poeticus Extract Narcissus Pseudonarcissus Flower Extract Narcissus Jonquilla Extract Narcissus Tazetta Extract | JA6: Narcissus Poeticus Extract Narcissus Pseudonarcissus Flower Extract Narcissus Jonquilla Extract Narcissus Tazetta Extract | JC6: Narcissus Poeticus Extract Narcissus Pseudonarcissus Flower Extract Narcissus Jonquilla Extract Narcissus Tazetta Extract | JE6: Narcissus Poeticus Extract Narcissus Pseudonarcissus Flower Extract Narcissus Jonquilla Extract Narcissus Tazetta Extract | JG6: Pelargonium Graveolens Flower Oil | JI6: Pelargonium Graveolens Flower Oil | JK6: Pogostemon Cablin Oil | JM6: Pogostemon Cablin Oil | JO6: Rosa Damascena Flower Oil; Rosa Damascena Flower Extract Rosa Alba Flower Oil; Rosa Alba Flower Extract Rosa Canina Fruit Oil Rosa Centifolia Flower Oil; Rosa Centifolia Flower Extract Rosa Gallica Flower Oil Rosa Moschata Flower Oil Rosa Rugosa Flower Oil | JQ6: Rosa Damascena Flower Oil; Rosa Damascena Flower Extract Rosa Alba Flower Oil; Rosa Alba Flower Extract Rosa Canina Fruit Oil Rosa Centifolia Flower Oil; Rosa Centifolia Flower Extract Rosa Gallica Flower Oil Rosa Moschata Flower Oil Rosa Rugosa Flower Oil | JS6: Rosa Damascena Flower Oil; Rosa Damascena Flower Extract Rosa Alba Flower Oil; Rosa Alba Flower Extract Rosa Canina Fruit Oil Rosa Centifolia Flower Oil; Rosa Centifolia Flower Extract Rosa Gallica Flower Oil Rosa Moschata Flower Oil Rosa Rugosa Flower Oil | JU6: Rosa Damascena Flower Oil; Rosa Damascena Flower Extract Rosa Alba Flower Oil; Rosa Alba Flower Extract Rosa Canina Fruit Oil Rosa Centifolia Flower Oil; Rosa Centifolia Flower Extract Rosa Gallica Flower Oil Rosa Moschata Flower Oil Rosa Rugosa Flower Oil | JW6: Rosa Damascena Flower Oil; Rosa Damascena Flower Extract Rosa Alba Flower Oil; Rosa Alba Flower Extract Rosa Canina Fruit Oil Rosa Centifolia Flower Oil; Rosa Centifolia Flower Extract Rosa Gallica Flower Oil Rosa Moschata Flower Oil Rosa Rugosa Flower Oil | JY6: Rosa Damascena Flower Oil; Rosa Damascena Flower Extract Rosa Alba Flower Oil; Rosa Alba Flower Extract Rosa Canina Fruit Oil Rosa Centifolia Flower Oil; Rosa Centifolia Flower Extract Rosa Gallica Flower Oil Rosa Moschata Flower Oil Rosa Rugosa Flower Oil | KA6: Rosa Damascena Flower Oil; Rosa Damascena Flower Extract Rosa Alba Flower Oil; Rosa Alba Flower Extract Rosa Canina Fruit Oil Rosa Centifolia Flower Oil; Rosa Centifolia Flower Extract Rosa Gallica Flower Oil Rosa Moschata Flower Oil Rosa Rugosa Flower Oil | KC6: Santalum Album Oil | KE6: Santalum Album Oil | KG6: Eugenyl Acetate | KI6: Geranyl Acetate | KK6: Isoeugenyl Acetate | KM6: Pinene | KO6: Pinene | KQ6: Pinene | KS6: Pinene | KU6: Cinnamyl alcohol | KW6: Eugenol | KY6: Hydroxycitronellal | LA6: Amyl cinnamal | LC6: Amylcinnamyl alcohol | LE6: Benzyl salicylate | LG6: Cinnamal | LI6: Coumarin | LK6: Geraniol | LM6: Anise alcohol | LO6: Benzyl cinnamate | LQ6: Farnesol | LS6: Linalool | LU6: Benzyl benzoate | LW6: Hexyl cinnamal | LY6: Methyl 2-octynoate | MA6: Alpha isomethyl ionone | MC6: butylphenyl methylpropional | ME6: evernia furfuracea (treemoss) extract | MG6: evernia prunastri (oak moss) extract | MI6: hydroxyisohexyl 3-cyclohexene carboxaldehyde
A7: Référence MP interne RM internal reference | B7: Description | C7: INCI | D7: Dénomination commerciale MP Commercial RM name | E7: % (m / m) MP dans la formule % (w / w) RM in the formula | F7: N°CAS | G7: 100-51-6 | I7: 92-48-8 | K7: 5392-40-5 | M7: 141-27-5 | O7: 106-26-3 | Q7: 97-54-1 | S7: 5932-68-3 | U7: 5912-86-7 | W7: 106-22-9 | Y7: 26489-01-0 | AA7: 1117-61-9 | AC7: 7540-51-4 | AE7: 138-86-3 | AG7: 7705-14-8 | AI7: 5989-27-5 | AK7: 5989-54-8 | AM7: 90082-72-7 | AO7: 97676-05-6 | AQ7: 92201-55-3 | AS7: 8023-85-6 | AU7: 9005-90-7 | AW7: 8006-64-2 | AY7: 8052-14-0 | BA7: 99-86-5 | BC7: 586-62-9 | BE7: 8007-00-9 | BG7: 43052-87-5 | BI7: 23726-94-5 | BK7: 24720-09-0 | BM7: 23696-85-7 | BO7: 57378-68-4 | BQ7: 71048-82-3 | BS7: 23726-92-3 | BU7: 23726-91-2 | BW7: 17369-59-4 | BY7: 8024-12-2 | CA7: 85116-63-8 | CC7: 32388-55-9 | CE7: 2050-08-0 | CG7: 104-46-1 | CI7: 4180-23-8 | CK7: 100-52-7 | CM7: 76-22-2 | CO7: 21368-68-3 | CQ7: 464-49-3 | CS7: 464-48-2 | CU7: 87-44-5 | CW7: 99-49-0 | CY7: 6485-40-1 | DA7: 2244-16-8 | DC7: 151-05-3 | DE7: 109-29-5 | DG7: 1222-05-5 | DI7: 115-95-7 | DK7: 89-78-1 | DM7: 1490-04-6 | DO7: 2216-51-5 | DQ7: 15356-60-2 | DS7: 119-36-8 | DU7: 67801-20-1 | DW7: 90-02-8 | DY7: 11031-45-1 | EA7: 115-71-9 | EC7: 77-42-9 | EE7: 515-03-7 | EG7: 8000-41-7 | EI7: 98-55-5 | EK7: 138-87-4 | EM7: 586-81-2 | EO7: 54464-57-2 | EQ7: 54464-59-4 | ES7: 68155-66-8 | EU7: 68155-67-9 | EW7: 103694-68-4 | EY7: 121-33-5 | FA7: 83863-30-3 | FC7: 8006-81-3 | FE7: 68606-83-7 | FG7: 93686-30-7 | FI7: 8007-80-5 | FK7: 84961-46-6 | FM7: 8015-91-6 | FO7: 84649-98-9 | FQ7: 72968-50-4 | FS7: 8028-48-6 | FU7: 8016-38-4 | FW7: 68916-04-1 | FY7: 72968-50-4 | GA7: 97766-30-8 | GC7: 8028-48-6 | GE7: 8008-57-9 | GG7: 8007-75-8 | GI7: 89957-91-5 | GK7: 68648-33-9 | GM7: 8007-75-8 | GO7: 85049-52-1 | GQ7: 84929-31-7 | GS7: 8008-56-8 | GU7: 8007-02-1 | GW7: 89998-16-3 | GY7: 91844-92-7 | HA7: 97926-40-4 | HC7: 8000-48-4 | HE7: 8000-34-8 | HG7: 84961-50-2 | HI7: 8015-97-2 | HK7: 84776-64-7 | HM7: 90045-94-6 | HO7: 8022-96-6 | HQ7: 8024-43-9 | HS7: 90045-94-6 | HU7: 8000-27-9/ 85085-41-2 | HW7: 8002-41-3 | HY7: 8007-48-5 | IA7: 84603-73-6 | IC7: 91722-69-9 | IE7: 8022-15-9 | IG7: 93455-96-0 | II7: 93455-97-1 | IK7: 92623-76-2 | IM7: 8000-28-0 | IO7: 90063-37-9 | IQ7: 8006-90-4 | IS7: 84082-70-2 | IU7: 8008-79-5 | IW7: 84696-51-5 | IY7: 90064-26-9 | JA7: 68917-12-4 | JC7: 90064-27-0 | JE7: 90064-25-8 | JG7: 90082-51-2 | JI7: 8000-46-2 | JK7: 8014-09-3 | JM7: 84238-39-1 | JO7: 8007-01-0 | JQ7: 90106-38-0 | JS7: 93334-48-6 | JU7: 84696-47-9 | JW7: 84604-12-6 | JY7: 84604-13-7 | KA7: 92347-25-6 | KC7: 8006-87-9 | KE7: 84787-70-2 | KG7: 93-28-7 | KI7: 105-87-3 | KK7: 93-29-8 | KM7: 80-56-8 | KO7: 7785-70-8 | KQ7: 127-91-3 | KS7: 18172-67-3 | KU7: 104-54-1 | KW7: 97-53-0 | KY7: 107-75-5 | LA7: 122-40-7 | LC7: 101-85-9 | LE7: 118-58-1 | LG7: 104-55-2 | LI7: 91-64-5 | LK7: 106-24-1 | LM7: 105-13-5 | LO7: 103-41-3 | LQ7: 4602-84-0 | LS7: 78-70-6 | LU7: 120-51-4 | LW7: 101-86-0 | LY7: 111-12-6 | MA7: 127-51-5 | MC7: 80-54-6 | ME7: 90028-67-4 | MG7: 90028-68-5 | MI7: 31906-04-4
F8: Groupements | K8: Citral | M8: Citral | O8: Citral | AM8: Pinus Mugo | AO8: Pinus Pumila | AQ8: Cedrus Atlantica | AS8: Cedrus Atlantica | BE8: Myroxylon Pereirae Oil/Extract | BG8: Rose Ketones | BI8: Rose Ketones | BK8: Rose Ketones | BM8: Rose Ketones | BO8: Rose Ketones | BQ8: Rose Ketones | BS8: Rose Ketones | BU8: Rose Ketones | FA8: Cananga Odorata Oil/Extract | FC8: Cananga Odorata Oil/Extract | FE8: Cananga Odorata Oil/Extract | FG8: Cananga Odorata Oil/Extract | FQ8: Citrus Aurantium Flower Oil | FS8: Citrus Aurantium Flower Oil | FU8: Citrus Aurantium Flower Oil | FW8: Citrus Aurantium Peel oil | FY8: Citrus Aurantium Peel oil | GA8: Citrus Aurantium Peel oil | GC8: Citrus Aurantium Peel oil | GE8: Citrus Aurantium Peel oil | GU8: Lemongrass Oil | GW8: Lemongrass Oil | GY8: Lemongrass Oil | HA8: Eucalyptus Globulus Oil | HC8: Eucalyptus Globulus Oil | HE8: Eugenia Caryophyllus Oil | HG8: Eugenia Caryophyllus Oil | HI8: Eugenia Caryophyllus Oil | HK8: Jasmine Oil/Extract | HM8: Jasmine Oil/Extract | HO8: Jasmine Oil/Extract | HQ8: Jasmine Oil/Extract | HS8: Jasmine Oil/Extract | HU8: Juniperus Virginiana Oil | IC8: Lavandula Oil/Extract | IE8: Lavandula Oil/Extract | IG8: Lavandula Oil/Extract | II8: Lavandula Oil/Extract | IK8: Lavandula Oil/Extract | IM8: Lavandula Oil/Extract | IO8: Lavandula Oil/Extract | IY8: Narcissus Extract | JA8: Narcissus Extract | JC8: Narcissus Extract | JE8: Narcissus Extract | JO8: Rose Flower Oil/Extract | JQ8: Rose Flower Oil/Extract | JS8: Rose Flower Oil/Extract | JU8: Rose Flower Oil/Extract | JW8: Rose Flower Oil/Extract | JY8: Rose Flower Oil/Extract | KA8: Rose Flower Oil/Extract
A9: MP201B | B9: =VLOOKUP(A9,'Allergènes 81'!$A$2:$F$65,2,0) -> Hydrolat Fleur d'Oranger BIO (conservé) | C9: =VLOOKUP(A9,'Allergènes 81'!$A$2:$E$36,3,0) -> Citrus Aurantium Amara Flower water 98% Aqua 1% Leuconostoc/Radish Root Ferment Filtrate 1% | D9: =VLOOKUP(A9,'Allergènes 81'!$A$2:$E$36,4,0) -> Hydrolat Fleur d'Oranger BIO (conservé) | E9: 25 | G9: =VLOOKUP(A9,'Allergènes 81'!A2:K68,7,0) -> 0 | H9: =(E9*G9)/100 -> 0 | I9: =VLOOKUP(A9,'Allergènes 81'!A2:K68,8,0) -> 0 | J9: =(E9*I9)/100 -> 0 | K9: =VLOOKUP(A9,'Allergènes 81'!A2:FR67,9,0) -> 0 | L9: =(E9*K9)/100 -> 0 | M9: =VLOOKUP(A9,'Allergènes 81'!A2:FR67,10,0) -> 0 | N9: =(E9*M9)/100 -> 0 | O9: =VLOOKUP(A9,'Allergènes 81'!A2:FR67,11,0) -> 0 | P9: =(E9*O9)/100 -> 0 | Q9: =VLOOKUP(A9,'Allergènes 81'!A2:FR67,12,0) -> 0 | R9: =(F9*Q9)/100 -> 0 | S9: =VLOOKUP(A9,'Allergènes 81'!A2:FR67,13,0) -> 0 | T9: =(F9*S9)/100 -> 0 | U9: =VLOOKUP(A9,'Allergènes 81'!A2:FR67,14,0) -> 0 | V9: =(E9*U9)/100 -> 0 | W9: =VLOOKUP(A9,'Allergènes 81'!A2:FR67,15,0) -> 0 | X9: =(E9*W9)/100 -> 0 | Y9: =VLOOKUP(A9,'Allergènes 81'!A2:FR67,16,0) -> 0 | Z9: =(E9*Y9)/100 -> 0 | AA9: =VLOOKUP(A9,'Allergènes 81'!A2:FR67,17,0) -> 0 | AB9: =(E9*AA9)/100 -> 0 | AC9: =VLOOKUP(A9,'Allergènes 81'!A2:FR67,18,0) -> 0 | AD9: =(E9*AA9)/100 -> 0 | AE9: =VLOOKUP(A9,'Allergènes 81'!A2:FR67,19,0) -> 0 | AF9: =(E9*AE9)/100 -> 0 | AG9: =VLOOKUP(A9,'Allergènes 81'!A2:FR67,20,0) -> 0 | AH9: =(E9*AG9)/100 -> 0 | AI9: =VLOOKUP(A9,'Allergènes 81'!A2:FR67,21,0) -> 0 | AJ9: =(E9*AI9)/100 -> 0 | AK9: =VLOOKUP(A9,'Allergènes 81'!A2:FR67,22,0) -> 0 | AL9: =(E9*AK9)/100 -> 0 | AM9: =VLOOKUP(A9,'Allergènes 81'!A2:FR67,23,0) -> 0 | AN9: =(E9*AM9)/100 -> 0 | AO9: =VLOOKUP(A9,'Allergènes 81'!A2:FR67,24,0) -> 0 | AP9: =(E9*AO9)/100 -> 0 | AQ9: =VLOOKUP(A9,'Allergènes 81'!A2:FR67,25,0) -> 0 | AR9: =(E9*AQ9)/100 -> 0 | AS9: =VLOOKUP(A9,'Allergènes 81'!A2:FR67,26,0) -> 0 | AT9: =(E9*AS9)/100 -> 0 | AU9: =VLOOKUP(A9,'Allergènes 81'!A2:FR67,27,0) -> 0 | AV9: =(E9*AU9)/100 -> 0 | AW9: =VLOOKUP(A9,'Allergènes 81'!A2:FR67,28,0) -> 0 | AX9: =(E9*AW9)/100 -> 0 | AY9: =VLOOKUP(A9,'Allergènes 81'!A2:FR67,29,0) -> 0 | AZ9: =(E9*AY9)/100 -> 0 | BA9: =VLOOKUP(A9,'Allergènes 81'!A2:FR67,30,0) -> 0 | BB9: =(E9*BA9)/100 -> 0 | BC9: =VLOOKUP(A9,'Allergènes 81'!A2:FR67,31,0) -> 0 | BD9: =(E9*BC9)/100 -> 0 | BE9: =VLOOKUP(A9,'Allergènes 81'!A2:FR67,32,0) -> 0 | BF9: =(E9*BE9)/100 -> 0 | BG9: =VLOOKUP(A9,'Allergènes 81'!A2:FR67,33,0) -> 0 | BH9: =(E9*BG9)/100 -> 0 | BI9: =VLOOKUP(A9,'Allergènes 81'!A2:FR67,34,0) -> 0 | BJ9: =(E9*BI9)/100 -> 0 | BK9: =VLOOKUP(A9,'Allergènes 81'!A2:FR67,35,0) -> 0 | BL9: =(E9*BK9)/100 -> 0 | BM9: =VLOOKUP(A9,'Allergènes 81'!A2:FR67,36,0) -> 0 | BN9: =(E9*BK9)/100 -> 0 | BO9: =VLOOKUP(A9,'Allergènes 81'!A2:FR67,37,0) -> 0 | BP9: =(E9*BO9)/100 -> 0 | BQ9: =VLOOKUP(A9,'Allergènes 81'!A2:FR67,38,0) -> 0 | BR9: =(E9*BQ9)/100 -> 0 | BS9: =VLOOKUP(A9,'Allergènes 81'!A2:FR67,39,0) -> 0 | BT9: =(E9*BS9)/100 -> 0 | BU9: =VLOOKUP(A9,'Allergènes 81'!A2:FR67,40,0) -> 0 | BV9: =(E9*BU9)/100 -> 0 | BW9: =VLOOKUP(A9,'Allergènes 81'!A2:FR67,41,0) -> 0 | BX9: =(E9*BW9)/100 -> 0 | BY9: =VLOOKUP(A9,'Allergènes 81'!A2:FR67,42,0) -> 0 | BZ9: =(E9*BY9)/100 -> 0 | CA9: =VLOOKUP(A9,'Allergènes 81'!A2:FR67,43,0) -> 0 | CB9: =(E9*CA9)/100 -> 0 | CC9: =VLOOKUP(A9,'Allergènes 81'!A2:FR67,44,0) -> 0 | CD9: =(E9*CC9)/100 -> 0 | CE9: =VLOOKUP(A9,'Allergènes 81'!A2:FR67,45,0) -> 0 | CF9: =(E9*CE9)/100 -> 0 | CG9: =VLOOKUP(A9,'Allergènes 81'!A2:FR67,46,0) -> 0 | CH9: =(E9*CG9)/100 -> 0 | CI9: =VLOOKUP(A9,'Allergènes 81'!A2:FR67,47,0) -> 0 | CJ9: =(E9*CI9)/100 -> 0 | CK9: =VLOOKUP(A9,'Allergènes 81'!A2:FR67,48,0) -> 0 | CL9: =(E9*CK9)/100 -> 0 | CM9: =VLOOKUP(A9,'Allergènes 81'!A2:FR67,49,0) -> 0 | CN9: =(E9*CM9)/100 -> 0 | CO9: =VLOOKUP(A9,'Allergènes 81'!A2:FR67,50,0) -> 0 | CP9: =(E9*CO9)/100 -> 0 | CQ9: =VLOOKUP(A9,'Allergènes 81'!A2:FR67,51,0) -> 0 | CR9: =(E9*CQ9)/100 -> 0 | CS9: =VLOOKUP(A9,'Allergènes 81'!A2:FR67,52,0) -> 0 | CT9: =(E9*CS9)/100 -> 0 | CU9: =VLOOKUP(A9,'Allergènes 81'!A2:FR67,53,0) -> 0 | CV9: =(E9*CU9)/100 -> 0 | CW9: =VLOOKUP(A9,'Allergènes 81'!A2:FR67,54,0) -> 0 | CX9: =(E9*CW9)/100 -> 0 | CY9: =VLOOKUP(A9,'Allergènes 81'!A2:FR67,55,0) -> 0 | CZ9: =(E9*CY9)/100 -> 0 | DA9: =VLOOKUP(A9,'Allergènes 81'!A2:FR67,56,0) -> 0 | DB9: =(E9*DA9)/100 -> 0 | DC9: =VLOOKUP(A9,'Allergènes 81'!A2:FR67,57,0) -> 0 | DD9: =(E9*DC9)/100 -> 0 | DE9: =VLOOKUP(A9,'Allergènes 81'!A2:FR67,58,0) -> 0 | DF9: =(E9*DE9)/100 -> 0 | DG9: =VLOOKUP(A9,'Allergènes 81'!A2:FR67,59,0) -> 0 | DH9: =(E9*DG9)/100 -> 0 | DI9: =VLOOKUP(A9,'Allergènes 81'!A2:FR67,60,0) -> 0 | DJ9: =(E9*DI9)/100 -> 0 | DK9: =VLOOKUP(A9,'Allergènes 81'!A2:FR67,61,0) -> 0 | DL9: =(E9*DK9)/100 -> 0 | DM9: =VLOOKUP(A9,'Allergènes 81'!A2:FR67,62,0) -> 0 | DN9: =(E9*DM9)/100 -> 0 | DO9: =VLOOKUP(A9,'Allergènes 81'!A2:FR67,63,0) -> 0 | DP9: =(E9*DO9)/100 -> 0 | DQ9: =VLOOKUP(A9,'Allergènes 81'!A2:FR67,64,0) -> 0 | DR9: =(E9*DQ9)/100 -> 0 | DS9: =VLOOKUP(A9,'Allergènes 81'!A2:FR67,65,0) -> 0 | DT9: =(E9*DS9)/100 -> 0 | DU9: =VLOOKUP(A9,'Allergènes 81'!A2:FR67,66,0) -> 0 | DV9: =(E9*DU9)/100 -> 0 | DW9: =VLOOKUP(A9,'Allergènes 81'!A2:FR67,67,0) -> 0 | DX9: =(E9*DW9)/100 -> 0 | DY9: =VLOOKUP(A9,'Allergènes 81'!A2:FR67,68,0) -> 0 | DZ9: =(E9*DY9)/100 -> 0 | EA9: =VLOOKUP(A9,'Allergènes 81'!A2:FR67,69,0) -> 0 | EB9: =(E9*EA9)/100 -> 0 | EC9: =VLOOKUP(A9,'Allergènes 81'!A2:FR67,70,0) -> 0 | ED9: =(E9*EC9)/100 -> 0 | EE9: =VLOOKUP(A9,'Allergènes 81'!A2:FR67,71,0) -> 0 | EF9: =(E9*EE9)/100 -> 0 | EG9: =VLOOKUP(A9,'Allergènes 81'!A2:FR67,72,0) -> 0.015 | EH9: =(E9*EG9)/100 -> 0.00375 | EI9: =VLOOKUP(A9,'Allergènes 81'!A2:FR67,73,0) -> 0 | EJ9: =(E9*EI9)/100 -> 0 | EK9: =VLOOKUP(A9,'Allergènes 81'!A2:FR67,74,0) -> 0 | EL9: =(E9*EK9)/100 -> 0 | EM9: =VLOOKUP(A9,'Allergènes 81'!A2:FR67,75,0) -> 0 | EN9: =(E9*EM9)/100 -> 0 | EO9: =VLOOKUP(A9,'Allergènes 81'!A2:FR67,76,0) -> 0 | EP9: =(E9*EO9)/100 -> 0 | EQ9: =VLOOKUP(A9,'Allergènes 81'!A2:FR67,77,0) -> 0 | ER9: =(E9*EQ9)/100 -> 0 | ES9: =VLOOKUP(A9,'Allergènes 81'!A2:FR67,78,0) -> 0 | ET9: =(E9*ES9)/100 -> 0 | EU9: =VLOOKUP(A9,'Allergènes 81'!A2:FR67,79,0) -> 0 | EV9: =(E9*EU9)/100 -> 0 | EW9: =VLOOKUP(A9,'Allergènes 81'!A2:FR67,80,0) -> 0 | EX9: =(E9*EW9)/100 -> 0 | EY9: =VLOOKUP(A9,'Allergènes 81'!A2:FR67,81,0) -> 0 | EZ9: =(E9*EY9)/100 -> 0 | FA9: =VLOOKUP(A9,'Allergènes 81'!A2:FR67,82,0) -> 0 | FB9: =(E9*FA9)/100 -> 0 | FC9: =VLOOKUP(A9,'Allergènes 81'!A2:FR67,83,0) -> 0 | FD9: =(E9*FC9)/100 -> 0 | FE9: =VLOOKUP(A9,'Allergènes 81'!A2:FR67,84,0) -> 0 | FF9: =(E9*FE9)/100 -> 0 | FG9: =VLOOKUP(A9,'Allergènes 81'!A2:FR67,85,0) -> 0 | FH9: =(E9*FG9)/100 -> 0 | FI9: =VLOOKUP(A9,'Allergènes 81'!A2:FR67,86,0) -> 0 | FJ9: =(E9*FI9)/100 -> 0 | FK9: =VLOOKUP(A9,'Allergènes 81'!A2:FR67,87,0) -> 0 | FL9: =(E9*FK9)/100 -> 0 | FM9: =VLOOKUP(A9,'Allergènes 81'!A2:FR67,88,0) -> 0 | FN9: =(E9*FM9)/100 -> 0 | FO9: =VLOOKUP(A9,'Allergènes 81'!A2:FR67,89,0) -> 0 | FP9: =(E9*FO9)/100 -> 0 | FQ9: =VLOOKUP(A9,'Allergènes 81'!A2:FR67,90,0) -> 0.03 | FR9: =(E9*FQ9)/100 -> 0.0075 | FS9: =VLOOKUP(A9,'Allergènes 81'!A2:FR67,91,0) -> 0 | FT9: =(E9*FS9)/100 -> 0 | FU9: =VLOOKUP(A9,'Allergènes 81'!A2:FR67,92,0) -> 0 | FV9: =(E9*FU9)/100 -> 0 | FW9: =VLOOKUP(A9,'Allergènes 81'!A2:FR67,93,0) -> 0 | FX9: =(E9*FW9)/100 -> 0 | FY9: =VLOOKUP(A9,'Allergènes 81'!A2:FR67,94,0) -> 0 | FZ9: =(E9*FY9)/100 -> 0 | GA9: =VLOOKUP(A9,'Allergènes 81'!A2:FR67,95,0) -> 0 | GB9: =(E9*GA9)/100 -> 0 | GC9: =VLOOKUP(A9,'Allergènes 81'!A2:FR67,96,0) -> 0 | GD9: =(E9*GC9)/100 -> 0 | GE9: =VLOOKUP(A9,'Allergènes 81'!A2:FR67,97,0) -> 0 | GF9: =(E9*GE9)/100 -> 0 | GG9: =VLOOKUP(A9,'Allergènes 81'!A2:FR67,98,0) -> 0 | GH9: =(E9*GG9)/100 -> 0 | GI9: =VLOOKUP(A9,'Allergènes 81'!A2:FR67,99,0) -> 0 | GJ9: =(E9*GI9)/100 -> 0 | GK9: =VLOOKUP(A9,'Allergènes 81'!A2:FR67,100,0) -> 0 | GL9: =(E9*GK9)/100 -> 0 | GM9: =VLOOKUP(A9,'Allergènes 81'!A2:FR67,101,0) -> 0 | GN9: =(E9*GM9)/100 -> 0 | GO9: =VLOOKUP(A9,'Allergènes 81'!A2:FR67,102,0) -> 0 | GP9: =(E9*GO9)/100 -> 0 | GQ9: =VLOOKUP(A9,'Allergènes 81'!A2:FR67,103,0) -> 0 | GR9: =(E9*GQ9)/100 -> 0 | GS9: =VLOOKUP(A9,'Allergènes 81'!A2:FR67,104,0) -> 0 | GT9: =(E9*GS9)/100 -> 0 | GU9: =VLOOKUP(A9,'Allergènes 81'!A2:FR67,105,0) -> 0 | GV9: =(E9*GU9)/100 -> 0 | GW9: =VLOOKUP(A9,'Allergènes 81'!A2:FR67,106,0) -> 0 | GX9: =(E9*GW9)/100 -> 0 | GY9: =VLOOKUP(A9,'Allergènes 81'!A2:FR67,107,0) -> 0 | GZ9: =(E9*GY9)/100 -> 0 | HA9: =VLOOKUP(A9,'Allergènes 81'!A2:FR67,108,0) -> 0 | HB9: =(E9*HA9)/100 -> 0 | HC9: =VLOOKUP(A9,'Allergènes 81'!A2:FR67,109,0) -> 0 | HD9: =(E9*HC9)/100 -> 0 | HE9: =VLOOKUP(A9,'Allergènes 81'!A2:FR67,110,0) -> 0 | HF9: =(E9*HE9)/100 -> 0 | HG9: =VLOOKUP(A9,'Allergènes 81'!A2:FR67,111,0) -> 0 | HH9: =(E9*HG9)/100 -> 0 | HI9: =VLOOKUP(A9,'Allergènes 81'!A2:FR67,112,0) -> 0 | HJ9: =(E9*HI9)/100 -> 0 | HK9: =VLOOKUP(A9,'Allergènes 81'!A2:FR67,113,0) -> 0 | HL9: =(E9*HK9)/100 -> 0 | HM9: =VLOOKUP(A9,'Allergènes 81'!A2:FR67,114,0) -> 0 | HN9: =(E9*HM9)/100 -> 0 | HO9: =VLOOKUP(A9,'Allergènes 81'!A2:FR67,115,0) -> 0 | HP9: =(E9*HO9)/100 -> 0 | HQ9: =VLOOKUP(A9,'Allergènes 81'!A2:FR67,116,0) -> 0 | HR9: =(E9*HQ9)/100 -> 0 | HS9: =VLOOKUP(A9,'Allergènes 81'!A2:FR67,117,0) -> 0 | HT9: =(E9*HS9)/100 -> 0 | HU9: =VLOOKUP(A9,'Allergènes 81'!A2:FR67,118,0) -> 0 | HV9: =(E9*HU9)/100 -> 0 | HW9: =VLOOKUP(A9,'Allergènes 81'!A2:FR67,119,0) -> 0 | HX9: =(E9*HW9)/100 -> 0 | HY9: =VLOOKUP(A9,'Allergènes 81'!A2:FR67,120,0) -> 0 | HZ9: =(E9*HY9)/100 -> 0 | IA9: =VLOOKUP(A9,'Allergènes 81'!A2:FR67,121,0) -> 0 | IB9: =(E9*IA9)/100 -> 0 | IC9: =VLOOKUP(A9,'Allergènes 81'!A2:FR67,122,0) -> 0 | ID9: =(E9*IC9)/100 -> 0 | IE9: =VLOOKUP(A9,'Allergènes 81'!A2:FR67,123,0) -> 0 | IF9: =(E9*IE9)/100 -> 0 | IG9: =VLOOKUP(A9,'Allergènes 81'!A2:FR67,124,0) -> 0 | IH9: =(E9*IG9)/100 -> 0 | II9: =VLOOKUP(A9,'Allergènes 81'!A2:FR67,125,0) -> 0 | IJ9: =(E9*II9)/100 -> 0 | IK9: =VLOOKUP(A9,'Allergènes 81'!A2:FR67,126,0) -> 0 | IL9: =(E9*IK9)/100 -> 0 | IM9: =VLOOKUP(A9,'Allergènes 81'!A2:FR67,127,0) -> 0 | IN9: =(E9*IM9)/100 -> 0 | IO9: =VLOOKUP(A9,'Allergènes 81'!A2:FR67,128,0) -> 0 | IP9: =(E9*IO9)/100 -> 0 | IQ9: =VLOOKUP(A9,'Allergènes 81'!A2:FR67,129,0) -> 0 | IR9: =(E9*IQ9)/100 -> 0 | IS9: =VLOOKUP(A9,'Allergènes 81'!A2:FR67,130,0) -> 0 | IT9: =(E9*IS9)/100 -> 0 | IU9: =VLOOKUP(A9,'Allergènes 81'!A2:FR67,131,0) -> 0 | IV9: =(E9*IU9)/100 -> 0 | IW9: =VLOOKUP(A9,'Allergènes 81'!A2:FR67,132,0) -> 0 | IX9: =(E9*IW9)/100 -> 0 | IY9: =VLOOKUP(A9,'Allergènes 81'!A2:FR67,133,0) -> 0 | IZ9: =(E9*IY9)/100 -> 0 | JA9: =VLOOKUP(A9,'Allergènes 81'!A2:FR67,134,0) -> 0 | JB9: =(E9*JA9)/100 -> 0 | JC9: =VLOOKUP(A9,'Allergènes 81'!A2:FR67,135,0) -> 0 | JD9: =(E9*JC9)/100 -> 0 | JE9: =VLOOKUP(A9,'Allergènes 81'!A2:FR67,136,0) -> 0 | JF9: =(E9*JE9)/100 -> 0 | JG9: =VLOOKUP(A9,'Allergènes 81'!A2:FR67,137,0) -> 0 | JH9: =(E9*JG9)/100 -> 0 | JI9: =VLOOKUP(A9,'Allergènes 81'!A2:FR67,138,0) -> 0 | JJ9: =(E9*JI9)/100 -> 0 | JK9: =VLOOKUP(A9,'Allergènes 81'!A2:FR67,139,0) -> 0 | JL9: =(E9*JK9)/100 -> 0 | JM9: =VLOOKUP(A9,'Allergènes 81'!A2:FR67,140,0) -> 0 | JN9: =(E9*JM9)/100 -> 0 | JO9: =VLOOKUP(A9,'Allergènes 81'!A2:FR67,141,0) -> 0 | JP9: =(E9*JO9)/100 -> 0 | JQ9: =VLOOKUP(A9,'Allergènes 81'!A2:FR67,142,0) -> 0 | JR9: =(E9*JQ9)/100 -> 0 | JS9: =VLOOKUP(A9,'Allergènes 81'!A2:FR67,143,0) -> 0 | JT9: =(E9*JS9)/100 -> 0 | JU9: =VLOOKUP(A9,'Allergènes 81'!A2:FR67,144,0) -> 0 | JV9: =(E9*JU9)/100 -> 0 | JW9: =VLOOKUP(A9,'Allergènes 81'!A2:FR67,145,0) -> 0 | JX9: =(E9*JW9)/100 -> 0 | JY9: =VLOOKUP(A9,'Allergènes 81'!A2:FR67,146,0) -> 0 | JZ9: =(E9*JY9)/100 -> 0 | KA9: =VLOOKUP(A9,'Allergènes 81'!A2:FR67,147,0) -> 0 | KB9: =(E9*KA9)/100 -> 0 | KC9: =VLOOKUP(A9,'Allergènes 81'!A2:FR67,148,0) -> 0 | KD9: =(E9*KC9)/100 -> 0 | KE9: =VLOOKUP(A9,'Allergènes 81'!A2:FR67,149,0) -> 0 | KF9: =(E9*KE9)/100 -> 0 | KG9: =VLOOKUP(A9,'Allergènes 81'!A2:FR67,150,0) -> 0 | KH9: =(E9*KG9)/100 -> 0 | KI9: =VLOOKUP(A9,'Allergènes 81'!A2:FR67,151,0) -> 0.0001 | KJ9: =(E9*KI9)/100 -> 2.5e-05 | KK9: =VLOOKUP(A9,'Allergènes 81'!A2:FR67,152,0) -> 0 | KL9: =(E9*KK9)/100 -> 0 | KM9: =VLOOKUP(A9,'Allergènes 81'!A2:FR67,153,0) -> 0 | KN9: =(E9*KM9)/100 -> 0 | KO9: =VLOOKUP(A9,'Allergènes 81'!A2:FR67,154,0) -> 0 | KP9: =(E9*KO9)/100 -> 0 | KQ9: =VLOOKUP(A9,'Allergènes 81'!A2:FR67,155,0) -> 0 | KR9: =(E9*KQ9)/100 -> 0 | KS9: =VLOOKUP(A9,'Allergènes 81'!A2:FR67,156,0) -> 0 | KT9: =(E9*KS9)/100 -> 0 | KU9: =VLOOKUP(A9,'Allergènes 81'!A2:FR67,157,0) -> 0 | KV9: =(E9*KU9)/100 -> 0 | KW9: =VLOOKUP(A9,'Allergènes 81'!A2:FR67,158,0) -> 0 | KX9: =(E9*KW9)/100 -> 0 | KY9: =VLOOKUP(A9,'Allergènes 81'!A2:FR67,159,0) -> 0 | KZ9: =(E9*KY9)/100 -> 0 | LA9: =VLOOKUP(A9,'Allergènes 81'!A2:FR67,160,0) -> 0 | LB9: =(E9*LA9)/100 -> 0 | LC9: =VLOOKUP(A9,'Allergènes 81'!A2:FR67,161,0) -> 0 | LD9: =(E9*LC9)/100 -> 0 | LE9: =VLOOKUP(A9,'Allergènes 81'!A2:FR67,162,0) -> 0 | LF9: =(E9*LE9)/100 -> 0 | LG9: =VLOOKUP(A9,'Allergènes 81'!A2:FR67,163,0) -> 0 | LH9: =(E9*LG9)/100 -> 0 | LI9: =VLOOKUP(A9,'Allergènes 81'!A2:FR67,164,0) -> 0 | LJ9: =(E9*LI9)/100 -> 0 | LK9: =VLOOKUP(A9,'Allergènes 81'!A2:FR67,165,0) -> 0.0003 | LL9: =(E9*LK9)/100 -> 7.5e-05 | LM9: =VLOOKUP(A9,'Allergènes 81'!A2:FR67,166,0) -> 0 | LN9: =(E9*LM9)/100 -> 0 | LO9: =VLOOKUP(A9,'Allergènes 81'!A2:FR67,167,0) -> 0 | LP9: =(E9*LO9)/100 -> 0 | LQ9: =VLOOKUP(A9,'Allergènes 81'!A2:FR67,168,0) -> 0 | LR9: =(E9*LQ9)/100 -> 0 | LS9: =VLOOKUP(A9,'Allergènes 81'!A2:FR67,169,0) -> 0.025 | LT9: =(E9*LS9)/100 -> 0.00625 | LU9: =VLOOKUP(A9,'Allergènes 81'!A2:FR67,170,0) -> 0 | LV9: =(E9*LU9)/100 -> 0 | LW9: =VLOOKUP(A9,'Allergènes 81'!A2:FR67,171,0) -> 0 | LX9: =(E9*LW9)/100 -> 0 | LY9: =VLOOKUP(A9,'Allergènes 81'!A2:FR67,172,0) -> 0 | LZ9: =(E9*LY9)/100 -> 0 | MA9: =VLOOKUP(A9,'Allergènes 81'!A2:FR67,173,0) -> 0 | MB9: =(E9*MA9)/100 -> 0 | MC9: =VLOOKUP(A9,'Allergènes 81'!A2:FR67,174,0) -> 0 | MD9: =(E9*MA9)/100 -> 0 | ME9: =VLOOKUP(A9,'Allergènes 81'!A2:FR67,175,0) -> #REF! | MF9: =(E9*MA9)/100 -> 0 | MG9: =VLOOKUP($A$9,'Allergènes 81'!$A$2:$FQ$34,176,0) -> #N/A | MH9: =(E9*MA9)/100 -> 0 | MI9: =VLOOKUP($A$9,'Allergènes 81'!$A$2:$FQ$34,177,0) -> #N/A | MJ9: =(E9*MA9)/100 -> 0
C12: % total de la substance allergène dans le produit fini / Total% of the allergenic substance in the finished product | G12: {=SUM(IFERROR(H9,))} -> 0 | I12: {=SUM(IFERROR(J9,))} -> 0 | K12: {=SUM(IFERROR(L9,))} -> 0 | M12: {=SUM(IFERROR(N9,))} -> 0 | O12: {=SUM(IFERROR(P9,))} -> 0 | Q12: {=SUM(IFERROR(R9,))} -> 0 | S12: {=SUM(IFERROR(T9,))} -> 0 | U12: {=SUM(IFERROR(V9,))} -> 0 | W12: {=SUM(IFERROR(X9,))} -> 0 | Y12: {=SUM(IFERROR(Z9,))} -> 0 | AA12: {=SUM(IFERROR(AB9,))} -> 0 | AC12: {=SUM(IFERROR(AD9,))} -> 0 | AE12: {=SUM(IFERROR(AF9,))} -> 0 | AG12: {=SUM(IFERROR(AH9,))} -> 0 | AI12: {=SUM(IFERROR(AJ9,))} -> 0 | AK12: {=SUM(IFERROR(AL9,))} -> 0 | AM12: {=SUM(IFERROR(AN9,))} -> 0 | AO12: {=SUM(IFERROR(AP9,))} -> 0 | AQ12: {=SUM(IFERROR(AR9,))} -> 0 | AS12: {=SUM(IFERROR(AT9,))} -> 0 | AU12: {=SUM(IFERROR(AV9,))} -> 0 | AW12: {=SUM(IFERROR(AX9,))} -> 0 | AY12: {=SUM(IFERROR(AZ9,))} -> 0 | BA12: {=SUM(IFERROR(BB9,))} -> 0 | BC12: {=SUM(IFERROR(BD9,))} -> 0 | BE12: {=SUM(IFERROR(BF9,))} -> 0 | BG12: {=SUM(IFERROR(BH9,))} -> 0 | BI12: {=SUM(IFERROR(BJ9,))} -> 0 | BK12: {=SUM(IFERROR(BL9,))} -> 0 | BM12: {=SUM(IFERROR(BN9,))} -> 0 | BO12: {=SUM(IFERROR(BP9,))} -> 0 | BQ12: {=SUM(IFERROR(BR9,))} -> 0 | BS12: {=SUM(IFERROR(BT9,))} -> 0 | BU12: {=SUM(IFERROR(BV9,))} -> 0 | BW12: {=SUM(IFERROR(BX9,))} -> 0 | BY12: {=SUM(IFERROR(BZ9,))} -> 0 | CA12: {=SUM(IFERROR(CB9,))} -> 0 | CC12: {=SUM(IFERROR(CD9,))} -> 0 | CE12: {=SUM(IFERROR(CF9,))} -> 0 | CG12: {=SUM(IFERROR(CH9,))} -> 0 | CI12: {=SUM(IFERROR(CJ9,))} -> 0 | CK12: {=SUM(IFERROR(CL9,))} -> 0 | CM12: {=SUM(IFERROR(CN9,))} -> 0 | CO12: {=SUM(IFERROR(CP9,))} -> 0 | CQ12: {=SUM(IFERROR(CR9,))} -> 0 | CS12: {=SUM(IFERROR(CT9,))} -> 0 | CU12: {=SUM(IFERROR(CV9,))} -> 0 | CW12: {=SUM(IFERROR(CX9,))} -> 0 | CY12: {=SUM(IFERROR(CZ9,))} -> 0 | DA12: {=SUM(IFERROR(DB9,))} -> 0 | DC12: {=SUM(IFERROR(DD9,))} -> 0 | DE12: {=SUM(IFERROR(DF9,))} -> 0 | DG12: {=SUM(IFERROR(DH9,))} -> 0 | DI12: {=SUM(IFERROR(DJ9,))} -> 0 | DK12: {=SUM(IFERROR(DL9,))} -> 0 | DM12: {=SUM(IFERROR(DN9,))} -> 0 | DO12: {=SUM(IFERROR(DP9,))} -> 0 | DQ12: {=SUM(IFERROR(DR9,))} -> 0 | DS12: {=SUM(IFERROR(DT9,))} -> 0 | DU12: {=SUM(IFERROR(DV9,))} -> 0 | DW12: {=SUM(IFERROR(DX9,))} -> 0 | DY12: {=SUM(IFERROR(DZ9,))} -> 0 | EA12: {=SUM(IFERROR(EB9,))} -> 0 | EC12: {=SUM(IFERROR(ED9,))} -> 0 | EE12: {=SUM(IFERROR(EF9,))} -> 0 | EG12: {=SUM(IFERROR(EH9,))} -> 0.00375 | EI12: {=SUM(IFERROR(EJ9,))} -> 0 | EK12: {=SUM(IFERROR(EL9,))} -> 0 | EM12: {=SUM(IFERROR(EN9,))} -> 0 | EO12: {=SUM(IFERROR(EP9,))} -> 0 | EQ12: {=SUM(IFERROR(ER9,))} -> 0 | ES12: {=SUM(IFERROR(ET9,))} -> 0 | EU12: {=SUM(IFERROR(EV9,))} -> 0 | EW12: {=SUM(IFERROR(EX9,))} -> 0 | EY12: {=SUM(IFERROR(EZ9,))} -> 0 | FA12: {=SUM(IFERROR(FB9,))} -> 0 | FC12: {=SUM(IFERROR(FD9,))} -> 0 | FE12: {=SUM(IFERROR(FF9,))} -> 0 | FG12: {=SUM(IFERROR(FH9,))} -> 0 | FI12: {=SUM(IFERROR(FJ9,))} -> 0 | FK12: {=SUM(IFERROR(FL9,))} -> 0 | FM12: {=SUM(IFERROR(FN9,))} -> 0 | FO12: {=SUM(IFERROR(FP9,))} -> 0 | FQ12: {=SUM(IFERROR(FR9,))} -> 0.0075 | FS12: {=SUM(IFERROR(FT9,))} -> 0 | FU12: {=SUM(IFERROR(FV9,))} -> 0 | FW12: {=SUM(IFERROR(FX9,))} -> 0 | FY12: {=SUM(IFERROR(FZ9,))} -> 0 | GA12: {=SUM(IFERROR(GB9,))} -> 0 | GC12: {=SUM(IFERROR(GD9,))} -> 0 | GE12: {=SUM(IFERROR(GF9,))} -> 0 | GG12: {=SUM(IFERROR(GH9,))} -> 0 | GI12: {=SUM(IFERROR(GJ9,))} -> 0 | GK12: {=SUM(IFERROR(GL9,))} -> 0 | GM12: {=SUM(IFERROR(GN9,))} -> 0 | GO12: {=SUM(IFERROR(GP9,))} -> 0 | GQ12: {=SUM(IFERROR(GR9,))} -> 0 | GS12: {=SUM(IFERROR(GT9,))} -> 0 | GU12: {=SUM(IFERROR(GV9,))} -> 0 | GW12: {=SUM(IFERROR(GX9,))} -> 0 | GY12: {=SUM(IFERROR(GZ9,))} -> 0 | HA12: {=SUM(IFERROR(HB9,))} -> 0 | HC12: {=SUM(IFERROR(HD9,))} -> 0 | HE12: {=SUM(IFERROR(HF9,))} -> 0 | HG12: {=SUM(IFERROR(HH9,))} -> 0 | HI12: {=SUM(IFERROR(HJ9,))} -> 0 | HK12: {=SUM(IFERROR(HL9,))} -> 0 | HM12: {=SUM(IFERROR(HN9,))} -> 0 | HO12: {=SUM(IFERROR(HP9,))} -> 0 | HQ12: {=SUM(IFERROR(HR9,))} -> 0 | HS12: {=SUM(IFERROR(HT9,))} -> 0 | HU12: {=SUM(IFERROR(HV9,))} -> 0 | HW12: {=SUM(IFERROR(HX9,))} -> 0 | HY12: {=SUM(IFERROR(HZ9,))} -> 0 | IA12: {=SUM(IFERROR(IB9,))} -> 0 | IC12: {=SUM(IFERROR(ID9,))} -> 0 | IE12: {=SUM(IFERROR(IF9,))} -> 0 | IG12: {=SUM(IFERROR(IH9,))} -> 0 | II12: {=SUM(IFERROR(IJ9,))} -> 0 | IK12: {=SUM(IFERROR(IL9,))} -> 0 | IM12: {=SUM(IFERROR(IN9,))} -> 0 | IO12: {=SUM(IFERROR(IP9,))} -> 0 | IQ12: {=SUM(IFERROR(IR9,))} -> 0 | IS12: {=SUM(IFERROR(IT9,))} -> 0 | IU12: {=SUM(IFERROR(IV9,))} -> 0 | IW12: {=SUM(IFERROR(IX9,))} -> 0 | IY12: {=SUM(IFERROR(IZ9,))} -> 0 | JA12: {=SUM(IFERROR(JB9,))} -> 0 | JC12: {=SUM(IFERROR(JD9,))} -> 0 | JE12: {=SUM(IFERROR(JF9,))} -> 0 | JG12: {=SUM(IFERROR(JH9,))} -> 0 | JI12: {=SUM(IFERROR(JJ9,))} -> 0 | JK12: {=SUM(IFERROR(JL9,))} -> 0 | JM12: {=SUM(IFERROR(JN9,))} -> 0 | JO12: {=SUM(IFERROR(JP9,))} -> 0 | JQ12: {=SUM(IFERROR(JR9,))} -> 0 | JS12: {=SUM(IFERROR(JT9,))} -> 0 | JU12: {=SUM(IFERROR(JV9,))} -> 0 | JW12: {=SUM(IFERROR(JX9,))} -> 0 | JY12: {=SUM(IFERROR(JZ9,))} -> 0 | KA12: {=SUM(IFERROR(KB9,))} -> 0 | KC12: {=SUM(IFERROR(KD9,))} -> 0 | KE12: {=SUM(IFERROR(KF9,))} -> 0 | KG12: {=SUM(IFERROR(KH9,))} -> 0 | KI12: {=SUM(IFERROR(KJ9,))} -> 2.5e-05 | KK12: {=SUM(IFERROR(KL9,))} -> 0 | KM12: {=SUM(IFERROR(KN9,))} -> 0 | KO12: {=SUM(IFERROR(KP9,))} -> 0 | KQ12: {=SUM(IFERROR(KR9,))} -> 0 | KS12: {=SUM(IFERROR(KT9,))} -> 0 | KU12: {=SUM(IFERROR(KV9,))} -> 0 | KW12: {=SUM(IFERROR(KX9,))} -> 0 | KY12: {=SUM(IFERROR(KZ9,))} -> 0 | LA12: {=SUM(IFERROR(LB9,))} -> 0 | LC12: {=SUM(IFERROR(LD9,))} -> 0 | LE12: {=SUM(IFERROR(LF9,))} -> 0 | LG12: {=SUM(IFERROR(LH9,))} -> 0 | LI12: {=SUM(IFERROR(LJ9,))} -> 0 | LK12: {=SUM(IFERROR(LL9,))} -> 7.5e-05 | LM12: {=SUM(IFERROR(LN9,))} -> 0 | LO12: {=SUM(IFERROR(LP9,))} -> 0 | LQ12: {=SUM(IFERROR(LR9,))} -> 0 | LS12: {=SUM(IFERROR(LT9,))} -> 0.00625 | LU12: {=SUM(IFERROR(LV9,))} -> 0 | LW12: {=SUM(IFERROR(LX9,))} -> 0 | LY12: {=SUM(IFERROR(LZ9,))} -> 0 | MA12: {=SUM(IFERROR(MB9,))} -> 0 | MC12: {=SUM(IFERROR(MD9,))} -> 0 | ME12: {=SUM(IFERROR(MF9,))} -> 0 | MG12: {=SUM(IFERROR(MH9,))} -> 0 | MI12: {=SUM(IFERROR(MJ9,))} -> 0
C13: POUR UN PRODUIT RINCE déclarabilité dans la composition qualitative ? FOR A RINCE PRODUCT: notication on the qualitative composition? | G13: =IF(G12>0.01,"OUI","/") -> / | I13: =IF(I12>0.01,"OUI","/") -> / | K13: =IF(K12>0.01,"OUI","/") -> / | M13: =IF(M12>0.01,"OUI","/") -> / | O13: =IF(O12>0.01,"OUI","/") -> / | Q13: =IF(Q12>0.01,"OUI","/") -> / | S13: =IF(S12>0.01,"OUI","/") -> / | U13: =IF(U12>0.01,"OUI","/") -> / | W13: =IF(W12>0.01,"OUI","/") -> / | Y13: =IF(Y12>0.01,"OUI","/") -> / | AA13: =IF(AA12>0.01,"OUI","/") -> / | AC13: =IF(AC12>0.01,"OUI","/") -> / | AE13: =IF(AE12>0.01,"OUI","/") -> / | AG13: =IF(AG12>0.01,"OUI","/") -> / | AI13: =IF(AI12>0.01,"OUI","/") -> / | AK13: =IF(AK12>0.01,"OUI","/") -> / | AM13: =IF(AM12>0.01,"OUI","/") -> / | AO13: =IF(AO12>0.01,"OUI","/") -> / | AQ13: =IF(AQ12>0.01,"OUI","/") -> / | AS13: =IF(AS12>0.01,"OUI","/") -> / | AU13: =IF(AU12>0.01,"OUI","/") -> / | AW13: =IF(AW12>0.01,"OUI","/") -> / | AY13: =IF(AY12>0.01,"OUI","/") -> / | BA13: =IF(BA12>0.01,"OUI","/") -> / | BC13: =IF(BC12>0.01,"OUI","/") -> / | BE13: =IF(BE12>0.01,"OUI","/") -> / | BG13: =IF(BG12>0.01,"OUI","/") -> / | BI13: =IF(BI12>0.01,"OUI","/") -> / | BK13: =IF(BK12>0.01,"OUI","/") -> / | BM13: =IF(BM12>0.01,"OUI","/") -> / | BO13: =IF(BO12>0.01,"OUI","/") -> / | BQ13: =IF(BQ12>0.01,"OUI","/") -> / | BS13: =IF(BS12>0.01,"OUI","/") -> / | BU13: =IF(BU12>0.01,"OUI","/") -> / | BW13: =IF(BW12>0.01,"OUI","/") -> / | BY13: =IF(BY12>0.01,"OUI","/") -> / | CA13: =IF(CA12>0.01,"OUI","/") -> / | CC13: =IF(CC12>0.01,"OUI","/") -> / | CE13: =IF(CE12>0.01,"OUI","/") -> / | CG13: =IF(CG12>0.01,"OUI","/") -> / | CI13: =IF(CI12>0.01,"OUI","/") -> / | CK13: =IF(CK12>0.01,"OUI","/") -> / | CM13: =IF(CM12>0.01,"OUI","/") -> / | CO13: =IF(CO12>0.01,"OUI","/") -> / | CQ13: =IF(CQ12>0.01,"OUI","/") -> / | CS13: =IF(CS12>0.01,"OUI","/") -> / | CU13: =IF(CU12>0.01,"OUI","/") -> / | CW13: =IF(CW12>0.01,"OUI","/") -> / | CY13: =IF(CY12>0.01,"OUI","/") -> / | DA13: =IF(DA12>0.01,"OUI","/") -> / | DC13: =IF(DC12>0.01,"OUI","/") -> / | DE13: =IF(DE12>0.01,"OUI","/") -> / | DG13: =IF(DG12>0.01,"OUI","/") -> / | DI13: =IF(DI12>0.01,"OUI","/") -> / | DK13: =IF(DK12>0.01,"OUI","/") -> / | DM13: =IF(DM12>0.01,"OUI","/") -> / | DO13: =IF(DO12>0.01,"OUI","/") -> / | DQ13: =IF(DQ12>0.01,"OUI","/") -> / | DS13: =IF(DS12>0.01,"OUI","/") -> / | DU13: =IF(DU12>0.01,"OUI","/") -> / | DW13: =IF(DW12>0.01,"OUI","/") -> / | DY13: =IF(DY12>0.01,"OUI","/") -> / | EA13: =IF(EA12>0.01,"OUI","/") -> / | EC13: =IF(EC12>0.01,"OUI","/") -> / | EE13: =IF(EE12>0.01,"OUI","/") -> / | EG13: =IF(EG12>0.01,"OUI","/") -> / | EI13: =IF(EI12>0.01,"OUI","/") -> / | EK13: =IF(EK12>0.01,"OUI","/") -> / | EM13: =IF(EM12>0.01,"OUI","/") -> / | EO13: =IF(EO12>0.01,"OUI","/") -> / | EQ13: =IF(EQ12>0.01,"OUI","/") -> / | ES13: =IF(ES12>0.01,"OUI","/") -> / | EU13: =IF(EU12>0.01,"OUI","/") -> / | EW13: =IF(EW12>0.01,"OUI","/") -> / | EY13: =IF(EY12>0.01,"OUI","/") -> / | FA13: =IF(FA12>0.01,"OUI","/") -> / | FC13: =IF(FC12>0.01,"OUI","/") -> / | FE13: =IF(FE12>0.01,"OUI","/") -> / | FG13: =IF(FG12>0.01,"OUI","/") -> / | FI13: =IF(FI12>0.01,"OUI","/") -> / | FK13: =IF(FK12>0.01,"OUI","/") -> / | FM13: =IF(FM12>0.01,"OUI","/") -> / | FO13: =IF(FO12>0.01,"OUI","/") -> / | FQ13: =IF(FQ12>0.01,"OUI","/") -> / | FS13: =IF(FS12>0.01,"OUI","/") -> / | FU13: =IF(FU12>0.01,"OUI","/") -> / | FW13: =IF(FW12>0.01,"OUI","/") -> / | FY13: =IF(FY12>0.01,"OUI","/") -> / | GA13: =IF(GA12>0.01,"OUI","/") -> / | GC13: =IF(GC12>0.01,"OUI","/") -> / | GE13: =IF(GE12>0.01,"OUI","/") -> / | GG13: =IF(GG12>0.01,"OUI","/") -> / | GI13: =IF(GI12>0.01,"OUI","/") -> / | GK13: =IF(GK12>0.01,"OUI","/") -> / | GM13: =IF(GM12>0.01,"OUI","/") -> / | GO13: =IF(GO12>0.01,"OUI","/") -> / | GQ13: =IF(GQ12>0.01,"OUI","/") -> / | GS13: =IF(GS12>0.01,"OUI","/") -> / | GU13: =IF(GU12>0.01,"OUI","/") -> / | GW13: =IF(GW12>0.01,"OUI","/") -> / | GY13: =IF(GY12>0.01,"OUI","/") -> / | HA13: =IF(HA12>0.01,"OUI","/") -> / | HC13: =IF(HC12>0.01,"OUI","/") -> / | HE13: =IF(HE12>0.01,"OUI","/") -> / | HG13: =IF(HG12>0.01,"OUI","/") -> / | HI13: =IF(HI12>0.01,"OUI","/") -> / | HK13: =IF(HK12>0.01,"OUI","/") -> / | HM13: =IF(HM12>0.01,"OUI","/") -> / | HO13: =IF(HO12>0.01,"OUI","/") -> / | HQ13: =IF(HQ12>0.01,"OUI","/") -> / | HS13: =IF(HS12>0.01,"OUI","/") -> / | HU13: =IF(HU12>0.01,"OUI","/") -> / | HW13: =IF(HW12>0.01,"OUI","/") -> / | HY13: =IF(HY12>0.01,"OUI","/") -> / | IA13: =IF(IA12>0.01,"OUI","/") -> / | IC13: =IF(IC12>0.01,"OUI","/") -> / | IE13: =IF(IE12>0.01,"OUI","/") -> / | IG13: =IF(IG12>0.01,"OUI","/") -> / | II13: =IF(II12>0.01,"OUI","/") -> / | IK13: =IF(IK12>0.01,"OUI","/") -> / | IM13: =IF(IM12>0.01,"OUI","/") -> / | IO13: =IF(IO12>0.01,"OUI","/") -> / | IQ13: =IF(IQ12>0.01,"OUI","/") -> / | IS13: =IF(IS12>0.01,"OUI","/") -> / | IU13: =IF(IU12>0.01,"OUI","/") -> / | IW13: =IF(IW12>0.01,"OUI","/") -> / | IY13: =IF(IY12>0.01,"OUI","/") -> / | JA13: =IF(JA12>0.01,"OUI","/") -> / | JC13: =IF(JC12>0.01,"OUI","/") -> / | JE13: =IF(JE12>0.01,"OUI","/") -> / | JG13: =IF(JG12>0.01,"OUI","/") -> / | JI13: =IF(JI12>0.01,"OUI","/") -> / | JK13: =IF(JK12>0.01,"OUI","/") -> / | JM13: =IF(JM12>0.01,"OUI","/") -> / | JO13: =IF(JO12>0.01,"OUI","/") -> / | JQ13: =IF(JQ12>0.01,"OUI","/") -> / | JS13: =IF(JS12>0.01,"OUI","/") -> / | JU13: =IF(JU12>0.01,"OUI","/") -> / | JW13: =IF(JW12>0.01,"OUI","/") -> / | JY13: =IF(JY12>0.01,"OUI","/") -> / | KA13: =IF(KA12>0.01,"OUI","/") -> / | KC13: =IF(KC12>0.01,"OUI","/") -> / | KE13: =IF(KE12>0.01,"OUI","/") -> / | KG13: =IF(KG12>0.01,"OUI","/") -> / | KI13: =IF(KI12>0.01,"OUI","/") -> / | KK13: =IF(KK12>0.01,"OUI","/") -> / | KM13: =IF(KM12>0.01,"OUI","/") -> / | KO13: =IF(KO12>0.01,"OUI","/") -> / | KQ13: =IF(KQ12>0.01,"OUI","/") -> / | KS13: =IF(KS12>0.01,"OUI","/") -> / | KU13: =IF(KU12>0.01,"OUI","/") -> / | KW13: =IF(KW12>0.01,"OUI","/") -> / | KY13: =IF(KY12>0.01,"OUI","/") -> / | LA13: =IF(LA12>0.01,"OUI","/") -> / | LC13: =IF(LC12>0.01,"OUI","/") -> / | LE13: =IF(LE12>0.01,"OUI","/") -> / | LG13: =IF(LG12>0.01,"OUI","/") -> / | LI13: =IF(LI12>0.01,"OUI","/") -> / | LK13: =IF(LK12>0.01,"OUI","/") -> / | LM13: =IF(LM12>0.01,"OUI","/") -> / | LO13: =IF(LO12>0.01,"OUI","/") -> / | LQ13: =IF(LQ12>0.01,"OUI","/") -> / | LS13: =IF(LS12>0.01,"OUI","/") -> / | LU13: =IF(LU12>0.01,"OUI","/") -> / | LW13: =IF(LW12>0.01,"OUI","/") -> / | LY13: =IF(LY12>0.01,"OUI","/") -> / | MA13: =IF(MA12>0.01,"OUI","/") -> /
C14: POUR UN PRODUIT NON RINCE déclarabilité dans la composition qualitative ? FOR A NON-RINCE PRODUCT: notification on the qualitative composition? | G14: =IF(G12>0.001,"OUI","/") -> / | I14: =IF(I12>0.001,"OUI","/") -> / | K14: =IF(K12>0.001,"OUI","/") -> / | M14: =IF(M12>0.001,"OUI","/") -> / | O14: =IF(O12>0.001,"OUI","/") -> / | Q14: =IF(Q12>0.001,"OUI","/") -> / | S14: =IF(S12>0.001,"OUI","/") -> / | U14: =IF(U12>0.001,"OUI","/") -> / | W14: =IF(W12>0.001,"OUI","/") -> / | Y14: =IF(Y12>0.001,"OUI","/") -> / | AA14: =IF(AA12>0.001,"OUI","/") -> / | AC14: =IF(AC12>0.001,"OUI","/") -> / | AE14: =IF(AE12>0.001,"OUI","/") -> / | AG14: =IF(AG12>0.001,"OUI","/") -> / | AI14: =IF(AI12>0.001,"OUI","/") -> / | AK14: =IF(AK12>0.001,"OUI","/") -> / | AM14: =IF(AM12>0.001,"OUI","/") -> / | AO14: =IF(AO12>0.001,"OUI","/") -> / | AQ14: =IF(AQ12>0.001,"OUI","/") -> / | AS14: =IF(AS12>0.001,"OUI","/") -> / | AU14: =IF(AU12>0.001,"OUI","/") -> / | AW14: =IF(AW12>0.001,"OUI","/") -> / | AY14: =IF(AY12>0.001,"OUI","/") -> / | BA14: =IF(BA12>0.001,"OUI","/") -> / | BC14: =IF(BC12>0.001,"OUI","/") -> / | BE14: =IF(BE12>0.001,"OUI","/") -> / | BG14: =IF(BG12>0.001,"OUI","/") -> / | BI14: =IF(BI12>0.001,"OUI","/") -> / | BK14: =IF(BK12>0.001,"OUI","/") -> / | BM14: =IF(BM12>0.001,"OUI","/") -> / | BO14: =IF(BO12>0.001,"OUI","/") -> / | BQ14: =IF(BQ12>0.001,"OUI","/") -> / | BS14: =IF(BS12>0.001,"OUI","/") -> / | BU14: =IF(BU12>0.001,"OUI","/") -> / | BW14: =IF(BW12>0.001,"OUI","/") -> / | BY14: =IF(BY12>0.001,"OUI","/") -> / | CA14: =IF(CA12>0.001,"OUI","/") -> / | CC14: =IF(CC12>0.001,"OUI","/") -> / | CE14: =IF(CE12>0.001,"OUI","/") -> / | CG14: =IF(CG12>0.001,"OUI","/") -> / | CI14: =IF(CI12>0.001,"OUI","/") -> / | CK14: =IF(CK12>0.001,"OUI","/") -> / | CM14: =IF(CM12>0.001,"OUI","/") -> / | CO14: =IF(CO12>0.001,"OUI","/") -> / | CQ14: =IF(CQ12>0.001,"OUI","/") -> / | CS14: =IF(CS12>0.001,"OUI","/") -> / | CU14: =IF(CU12>0.001,"OUI","/") -> / | CW14: =IF(CW12>0.001,"OUI","/") -> / | CY14: =IF(CY12>0.001,"OUI","/") -> / | DA14: =IF(DA12>0.001,"OUI","/") -> / | DC14: =IF(DC12>0.001,"OUI","/") -> / | DE14: =IF(DE12>0.001,"OUI","/") -> / | DG14: =IF(DG12>0.001,"OUI","/") -> / | DI14: =IF(DI12>0.001,"OUI","/") -> / | DK14: =IF(DK12>0.001,"OUI","/") -> / | DM14: =IF(DM12>0.001,"OUI","/") -> / | DO14: =IF(DO12>0.001,"OUI","/") -> / | DQ14: =IF(DQ12>0.001,"OUI","/") -> / | DS14: =IF(DS12>0.001,"OUI","/") -> / | DU14: =IF(DU12>0.001,"OUI","/") -> / | DW14: =IF(DW12>0.001,"OUI","/") -> / | DY14: =IF(DY12>0.001,"OUI","/") -> / | EA14: =IF(EA12>0.001,"OUI","/") -> / | EC14: =IF(EC12>0.001,"OUI","/") -> / | EE14: =IF(EE12>0.001,"OUI","/") -> / | EG14: =IF(EG12>0.001,"OUI","/") -> OUI | EI14: =IF(EI12>0.001,"OUI","/") -> / | EK14: =IF(EK12>0.001,"OUI","/") -> / | EM14: =IF(EM12>0.001,"OUI","/") -> / | EO14: =IF(EO12>0.001,"OUI","/") -> / | EQ14: =IF(EQ12>0.001,"OUI","/") -> / | ES14: =IF(ES12>0.001,"OUI","/") -> / | EU14: =IF(EU12>0.001,"OUI","/") -> / | EW14: =IF(EW12>0.001,"OUI","/") -> / | EY14: =IF(EY12>0.001,"OUI","/") -> / | FA14: =IF(FA12>0.001,"OUI","/") -> / | FC14: =IF(FC12>0.001,"OUI","/") -> / | FE14: =IF(FE12>0.001,"OUI","/") -> / | FG14: =IF(FG12>0.001,"OUI","/") -> / | FI14: =IF(FI12>0.001,"OUI","/") -> / | FK14: =IF(FK12>0.001,"OUI","/") -> / | FM14: =IF(FM12>0.001,"OUI","/") -> / | FO14: =IF(FO12>0.001,"OUI","/") -> / | FQ14: =IF(FQ12>0.001,"OUI","/") -> OUI | FS14: =IF(FS12>0.001,"OUI","/") -> / | FU14: =IF(FU12>0.001,"OUI","/") -> / | FW14: =IF(FW12>0.001,"OUI","/") -> / | FY14: =IF(FY12>0.001,"OUI","/") -> / | GA14: =IF(GA12>0.001,"OUI","/") -> / | GC14: =IF(GC12>0.001,"OUI","/") -> / | GE14: =IF(GE12>0.001,"OUI","/") -> / | GG14: =IF(GG12>0.001,"OUI","/") -> / | GI14: =IF(GI12>0.001,"OUI","/") -> / | GK14: =IF(GK12>0.001,"OUI","/") -> / | GM14: =IF(GM12>0.001,"OUI","/") -> / | GO14: =IF(GO12>0.001,"OUI","/") -> / | GQ14: =IF(GQ12>0.001,"OUI","/") -> / | GS14: =IF(GS12>0.001,"OUI","/") -> / | GU14: =IF(GU12>0.001,"OUI","/") -> / | GW14: =IF(GW12>0.001,"OUI","/") -> / | GY14: =IF(GY12>0.001,"OUI","/") -> / | HA14: =IF(HA12>0.001,"OUI","/") -> / | HC14: =IF(HC12>0.001,"OUI","/") -> / | HE14: =IF(HE12>0.001,"OUI","/") -> / | HG14: =IF(HG12>0.001,"OUI","/") -> / | HI14: =IF(HI12>0.001,"OUI","/") -> / | HK14: =IF(HK12>0.001,"OUI","/") -> / | HM14: =IF(HM12>0.001,"OUI","/") -> / | HO14: =IF(HO12>0.001,"OUI","/") -> / | HQ14: =IF(HQ12>0.001,"OUI","/") -> / | HS14: =IF(HS12>0.001,"OUI","/") -> / | HU14: =IF(HU12>0.001,"OUI","/") -> / | HW14: =IF(HW12>0.001,"OUI","/") -> / | HY14: =IF(HY12>0.001,"OUI","/") -> / | IA14: =IF(IA12>0.001,"OUI","/") -> / | IC14: =IF(IC12>0.001,"OUI","/") -> / | IE14: =IF(IE12>0.001,"OUI","/") -> / | IG14: =IF(IG12>0.001,"OUI","/") -> / | II14: =IF(II12>0.001,"OUI","/") -> / | IK14: =IF(IK12>0.001,"OUI","/") -> / | IM14: =IF(IM12>0.001,"OUI","/") -> / | IO14: =IF(IO12>0.001,"OUI","/") -> / | IQ14: =IF(IQ12>0.001,"OUI","/") -> / | IS14: =IF(IS12>0.001,"OUI","/") -> / | IU14: =IF(IU12>0.001,"OUI","/") -> / | IW14: =IF(IW12>0.001,"OUI","/") -> / | IY14: =IF(IY12>0.001,"OUI","/") -> / | JA14: =IF(JA12>0.001,"OUI","/") -> / | JC14: =IF(JC12>0.001,"OUI","/") -> / | JE14: =IF(JE12>0.001,"OUI","/") -> / | JG14: =IF(JG12>0.001,"OUI","/") -> / | JI14: =IF(JI12>0.001,"OUI","/") -> / | JK14: =IF(JK12>0.001,"OUI","/") -> / | JM14: =IF(JM12>0.001,"OUI","/") -> / | JO14: =IF(JO12>0.001,"OUI","/") -> / | JQ14: =IF(JQ12>0.001,"OUI","/") -> / | JS14: =IF(JS12>0.001,"OUI","/") -> / | JU14: =IF(JU12>0.001,"OUI","/") -> / | JW14: =IF(JW12>0.001,"OUI","/") -> / | JY14: =IF(JY12>0.001,"OUI","/") -> / | KA14: =IF(KA12>0.001,"OUI","/") -> / | KC14: =IF(KC12>0.001,"OUI","/") -> / | KE14: =IF(KE12>0.001,"OUI","/") -> / | KG14: =IF(KG12>0.001,"OUI","/") -> / | KI14: =IF(KI12>0.001,"OUI","/") -> / | KK14: =IF(KK12>0.001,"OUI","/") -> / | KM14: =IF(KM12>0.001,"OUI","/") -> / | KO14: =IF(KO12>0.001,"OUI","/") -> / | KQ14: =IF(KQ12>0.001,"OUI","/") -> / | KS14: =IF(KS12>0.001,"OUI","/") -> / | KU14: =IF(KU12>0.001,"OUI","/") -> / | KW14: =IF(KW12>0.001,"OUI","/") -> / | KY14: =IF(KY12>0.001,"OUI","/") -> / | LA14: =IF(LA12>0.001,"OUI","/") -> / | LC14: =IF(LC12>0.001,"OUI","/") -> / | LE14: =IF(LE12>0.001,"OUI","/") -> / | LG14: =IF(LG12>0.001,"OUI","/") -> / | LI14: =IF(LI12>0.001,"OUI","/") -> / | LK14: =IF(LK12>0.001,"OUI","/") -> / | LM14: =IF(LM12>0.001,"OUI","/") -> / | LO14: =IF(LO12>0.001,"OUI","/") -> / | LQ14: =IF(LQ12>0.001,"OUI","/") -> / | LS14: =IF(LS12>0.001,"OUI","/") -> OUI | LU14: =IF(LU12>0.001,"OUI","/") -> / | LW14: =IF(LW12>0.001,"OUI","/") -> / | LY14: =IF(LY12>0.001,"OUI","/") -> / | MA14: =IF(MA12>0.001,"OUI","/") -> /

Sheet Tests toxico
A4: Code | B4: Description | C4: Laboratoire | D4: Prix
A5: CT001 | B5: Challenge test ISO11930 | C5: QACS | D5: 260
A6: PT001 | B6: Patch test | C6: QACS | D6: 150
A7: PT002 | B7: Patch test with sensitive skin | C7: QACS | D7: 195
A8: SA001 | B8: Safety assessment EU Reg. 2023/1545_New Allergens List | C8: QACS | D8: 350
A9: DSOL001 | B9: Dossier complet solaire | C9: Hélioscience | D9: 650
A10: SCR001 | B10: Screaning in vitro | C10: Hélioscience | D10: 360
D11: 0
D12: 0
D13: 0
D14: 0
D15: 0
D16: 0
D17: 0
D18: 0
D19: 0
D20: 0
D21: 0
D22: 0
... D24: 0

Sheet Gamme bébé
A1: Nouvelles MPs
A2: Produit fini | B2: Code MP | C2: Nom commercial | D2: INCI | E2: Fournisseur | F2: Autre fournisseur | G2: % utilisé | H2: Prix €/kg HT | I2: MOQ | J2: Remarques | K2: Contact | L2: Délais livraison | M2: DLUO | N2: Gestion DLUO | O2: Packaging
A3: Crème douceur lactée | B3: MP205B | C3: =VLOOKUP(B3,Liste!A1:O1214,2,0) -> Hydrolat de lavande fine sauvage BIO | D3: Lavandula Angustifolia Flower Water* | E3: =VLOOKUP(C3,Liste!B1:P1214,2,0) -> Florihana | F3: Helpac Gazignaire Interaxion | G3: 10 | H3: =VLOOKUP('Gamme bébé'!B3,Liste!A1:O1260,6,0) -> 11.93 | I3: 1L | K3: Milie | L3: 10j | M3: 6 mois | O3: Airless 50ml APTAR | P3: =SUM(G3:G18) -> 100
B4: MP358 | C4: =VLOOKUP(B4,Liste!A2:O1215,2,0) -> Montanov 202 | D4: Arachidyl Alcohol (and) Behenyl Alcohol (and) Arachidyl Glucoside | E4: =VLOOKUP(C4,Liste!B2:P1215,2,0) -> SEPPIC | F4: NA | G4: 5 | H4: =VLOOKUP('Gamme bébé'!B4,Liste!A2:O1261,6,0) -> 24.55 | I4: 25kg | J4: 1ère commande : 24,55€ puis 24,85€ | K4: Julie SANTACROCE julie.santacroce@airliquide.com | L4: 10j | M4: 60 mois
B5: MP015 | C5: =VLOOKUP(B5,Liste!A3:O1216,2,0) -> Opuntia Biocomplex SH | D5: Opuntia Ficus-Indica stem extract (and) Maltodextrin | E5: Bionap | F5: NA | G5: 1.4 | H5: =VLOOKUP('Gamme bébé'!B5,Liste!A3:O1262,6,0) -> 90 | I5: 5kg | K5: Marco MOLARO m.molaro@bionap.com | L5: ? | M5: 36 mois
B6: MP010 | C6: =VLOOKUP(B6,Liste!A4:O1217,2,0) -> CosmePhytami Oat | D6: Glycerin (and) Avena Sativa Kernel Extract | E6: =VLOOKUP(C6,Liste!B4:P1217,2,0) -> Alban Muller / CRODA | F6: NA | G6: 3 | H6: =VLOOKUP('Gamme bébé'!B6,Liste!A4:O1263,6,0) -> 32.82 | I6: 5kg | K6: Caroline QUENTIN | L6: 3-4 semaines | M6: 36 mois
B7: MP410 | C7: =VLOOKUP(B7,Liste!A5:O1218,2,0) -> Leucidal SF Max | D7: Lactobacillus Ferment | E7: =VLOOKUP(C7,Liste!B5:P1218,2,0) -> Active Micro | F7: NA | G7: 4 | H7: =VLOOKUP('Gamme bébé'!B7,Liste!A5:O1264,6,0) -> 39.43 | I7: 20kg | J7: 5kg : 54,54€ | K7: Active Concepts | L7: 15j | M7: 12 mois | N7: Tester les spec du produit. Si conforme, ralonger d'un an.
B8: MP408 | C8: =VLOOKUP(B8,Liste!A6:O1219,2,0) -> AMTicide Coconut | E8: =VLOOKUP(C8,Liste!B6:P1219,2,0) -> Active Micro | G8: 2 | H8: =VLOOKUP('Gamme bébé'!B8,Liste!A6:O1265,6,0) -> 48.8
B9: MP523 | C9: =VLOOKUP(B9,Liste!A5:O1218,2,0) -> Vanilline | E9: =VLOOKUP(C9,Liste!B5:P1218,2,0) -> Diffusions aromatiques | G9: 0.01 | H9: =VLOOKUP('Gamme bébé'!B9,Liste!A6:O1265,6,0) -> 520 | Q9: 1ère prod : 1000 unités
B10: MP401B | C10: =VLOOKUP(B10,Liste!A6:O1219,2,0) -> Glycerine BIO | E10: =VLOOKUP(C10,Liste!B6:P1219,2,0) -> IES Labo | G10: 8 | H10: =VLOOKUP('Gamme bébé'!B10,Liste!A7:O1266,6,0) -> 6.86
B11: MP350 | C11: =VLOOKUP(B11,Liste!A6:O1219,2,0) -> Gomme Xanthane | E11: =VLOOKUP(C11,Liste!B6:P1219,2,0) -> AMI | G11: 0.3 | H11: =VLOOKUP('Gamme bébé'!B11,Liste!A7:O1266,6,0) -> 23.33
B12: MP355 | C12: =VLOOKUP(B12,Liste!A7:O1220,2,0) -> Amigum-SM2 | E12: =VLOOKUP(C12,Liste!B7:P1220,2,0) -> Alban Muller | G12: 0.3 | H12: =VLOOKUP('Gamme bébé'!B12,Liste!A8:O1267,6,0) -> 222.2
B13: MP113B | C13: =VLOOKUP(B13,Liste!A8:O1221,2,0) -> HV Olive BIO | E13: =VLOOKUP(C13,Liste!B8:P1221,2,0) -> Cauvin | G13: 24 | H13: =VLOOKUP('Gamme bébé'!B13,Liste!A9:O1268,6,0) -> 10.43
B14: MP100B | C14: =VLOOKUP(B14,Liste!A9:O1222,2,0) -> Huile vegetale Noix de Coco Vierge bio | E14: =VLOOKUP(C14,Liste!B9:P1222,2,0) -> Aldivia | G14: 6 | H14: =VLOOKUP('Gamme bébé'!B14,Liste!A10:O1269,6,0) -> 12.14
B15: MP409 | C15: =VLOOKUP(B15,Liste!A10:O1223,2,0) -> Cosphaderm Sodium LAAS | E15: =VLOOKUP(C15,Liste!B10:P1223,2,0) -> Cosphatec | G15: 1 | H15: =VLOOKUP('Gamme bébé'!B15,Liste!A11:O1270,6,0) -> 94.57
B16: MP402 | C16: =VLOOKUP(B16,Liste!A11:O1224,2,0) -> Vitamine E | E16: =VLOOKUP(C16,Liste!B11:P1224,2,0) -> Azélis | G16: 0.07 | H16: =VLOOKUP('Gamme bébé'!B16,Liste!A12:O1271,6,0) -> 230.23
B17: MP403 | C17: =VLOOKUP(B17,Liste!A12:O1225,2,0) -> Acide lactique | E17: =VLOOKUP(C17,Liste!B12:P1225,2,0) -> AMI | G17: 0.4 | H17: =VLOOKUP('Gamme bébé'!B17,Liste!A13:O1272,6,0) -> 6.4
B18: MP000 | C18: =VLOOKUP(B18,Liste!A13:O1226,2,0) -> Eau déminéralisée | G18: =100-SUM(G3:G17) -> 34.52
A19: Baume fondant | B19: MP116 | C19: =VLOOKUP(B19,Liste!A5:O1218,2,0) -> Cire de candelilla | D19: Euphorbia Cerifera Cera | E19: =VLOOKUP(C19,Liste!B5:P1218,2,0) -> Ingretech | F19: Rossow | G19: 3 | H19: =VLOOKUP('Gamme bébé'!B19,Liste!A5:O1264,6,0) -> 28.9 | I19: 20kg | J19: Rossow 36€/kg | K19: Ingretech | L19: 10j | M19: 36 mois | N19: Avant ouverture : 36 mois Après ouverture : à conserver au frais | O19: Pot verre 100ml POHLI | P19: =SUM(G19:G24) -> 100
B20: MP115 | C20: =VLOOKUP(B20,Liste!A6:O1219,2,0) -> Cire de Sumac | D20: Rhus Verniciflua Peel Cera | E20: =VLOOKUP(C20,Liste!B6:P1219,2,0) -> Naturochim | F20: Ingretech | G20: 10 | H20: =VLOOKUP('Gamme bébé'!B20,Liste!A6:O1265,6,0) -> 40.53 | I20: 20kg | J20: Naturochim : 36,44€ les 40kg Ingretech : 50,30€/kg les 20kg | K20: Claudine COUMANNE direction@naturochim.com | L20: 10 semaines | M20: 36 mois
B21: MP113B | C21: =VLOOKUP(B21,Liste!A7:O1220,2,0) -> HV Olive BIO | E21: =VLOOKUP(C21,Liste!B7:P1220,2,0) -> Cauvin | G21: 61.45 | H21: =VLOOKUP('Gamme bébé'!B21,Liste!A7:O1266,6,0) -> 10.43
B22: MP523 | C22: =VLOOKUP(B22,Liste!A8:O1221,2,0) -> Vanilline | E22: =VLOOKUP(C22,Liste!B8:P1221,2,0) -> Diffusions aromatiques | G22: 0.05 | H22: =VLOOKUP('Gamme bébé'!B22,Liste!A8:O1267,6,0) -> 520
B23: MP114B | C23: =VLOOKUP(B23,Liste!A9:O1222,2,0) -> Macérât de lavande bio | E23: =VLOOKUP(C23,Liste!B9:P1222,2,0) -> La Canopée | G23: 25 | H23: =VLOOKUP('Gamme bébé'!B23,Liste!A9:O1268,6,0) -> 13.1
B24: MP402 | C24: =VLOOKUP(B24,Liste!A10:O1223,2,0) -> Vitamine E | E24: =VLOOKUP(C24,Liste!B10:P1223,2,0) -> Azélis | G24: 0.5 | H24: =VLOOKUP('Gamme bébé'!B24,Liste!A10:O1269,6,0) -> 230.23
A25: Pommade magique | B25: MP119B | C25: =VLOOKUP(B25,Liste!A7:O1220,2,0) -> Huile de cameline vierge BIO | D25: Camelina Sativa Seed Oil* | E25: Bertin | F25: Helpac | G25: 16 | H25: =VLOOKUP('Gamme bébé'!B25,Liste!A7:O1266,6,0) -> 12.67 | I25: 20L | J25: 12,63€/kg le fut de 220L | K25: Cauvin | L25: 10j | M25: 12 mois | N25: Tester les spec du produit. Si conforme, ralonger d'un an. | O25: Tube canule PET 30ml TUBEPLANT | P25: =SUM(G25:G32) -> 100
B26: MP113B | C26: =VLOOKUP(B26,Liste!A8:O1221,2,0) -> HV Olive BIO | E26: =VLOOKUP(C26,Liste!B8:P1221,2,0) -> Cauvin | F26: Helpac / Aldivia / Interaxion | G26: 56.95 | H26: =VLOOKUP('Gamme bébé'!B26,Liste!A8:O1267,6,0) -> 10.43
B27: MP407 | C27: =VLOOKUP(B27,Liste!A9:O1222,2,0) -> DUB MUG | E27: =VLOOKUP(C27,Liste!B9:P1222,2,0) -> Azelis | G27: 1
B28: MP115 | C28: =VLOOKUP(B28,Liste!A9:O1222,2,0) -> Cire de Sumac | E28: =VLOOKUP(C28,Liste!B9:P1222,2,0) -> Naturochim | F28: Ingretech | G28: 3.1 | H28: =VLOOKUP('Gamme bébé'!B28,Liste!A9:O1268,6,0) -> 40.53
B29: MP116 | C29: =VLOOKUP(B29,Liste!A10:O1223,2,0) -> Cire de candelilla | E29: =VLOOKUP(C29,Liste!B10:P1223,2,0) -> Ingretech | F29: Rossow | G29: 1.75 | H29: =VLOOKUP('Gamme bébé'!B29,Liste!A10:O1269,6,0) -> 28.9
B30: MP527 | C30: =VLOOKUP(B30,Liste!A11:O1224,2,0) -> Extrait CO2 Calendula Marigold flower | E30: =VLOOKUP(C30,Liste!B11:P1224,2,0) -> Flavex | G30: 1 | H30: =VLOOKUP('Gamme bébé'!B30,Liste!A11:O1270,6,0) -> 320
B31: MP117 | C31: =VLOOKUP(B31,Liste!A12:O1225,2,0) -> Viamerine 10 000 | E31: =VLOOKUP(C31,Liste!B12:P1225,2,0) -> Aldivia | G31: 20 | H31: =VLOOKUP('Gamme bébé'!B31,Liste!A12:O1271,6,0) -> 41.74
B32: MP402 | C32: =VLOOKUP(B32,Liste!A14:O1227,2,0) -> Vitamine E | E32: =VLOOKUP(C32,Liste!B14:P1227,2,0) -> Azélis | G32: 0.2 | H32: =VLOOKUP('Gamme bébé'!B32,Liste!A14:O1273,6,0) -> 230.23
A33: Gelée lavante fleur vanillée | B33: MP305 | C33: =VLOOKUP(B33,Liste!A8:O1221,2,0) -> Pureact Gluco D CO | D33: Decyl Glucoside 50%, Aqua 50% | E33: =VLOOKUP(C33,Liste!B8:P1221,2,0) -> Ingretech | F33: NA | G33: 6 | H33: =VLOOKUP('Gamme bébé'!B33,Liste!A8:O1267,6,0) -> 4.45 | J33: déjà commandé négocié à 3,85 | K33: Ingretech | L33: 4-6 mois | O33: Bouillote PET 200ml + chapeau chinois | P33: =SUM(G33:G45) -> 100
B34: MP359 | C34: =VLOOKUP(B34,Liste!A9:O1222,2,0) -> Holisurf HF | D34: Glycolipids | E34: =VLOOKUP(C34,Liste!B9:P1222,2,0) -> Ingretech | F34: NA | G34: 4 | H34: =VLOOKUP('Gamme bébé'!B34,Liste!A9:O1268,6,0) -> 12.5 | I34: 200kg | J34: 32,8€/kg pour 20kg | K34: Ingretech Julie Lanxade julie.lanxade@ingretech.fr | L34: 6 semaines
B35: MP204B | C35: =VLOOKUP(B35,Liste!A10:O1223,2,0) -> Hydrolat de fleur d'oranger (Néroli) BIO non conservé | D35: Citrus Aurantium Amara Flower Water* | E35: =VLOOKUP(C35,Liste!B10:P1223,2,0) -> Florihana | F35: Helpac Gazignaire | G35: 20 | H35: =VLOOKUP('Gamme bébé'!B35,Liste!A10:O1269,6,0) -> 11.93 | I35: 1L | J35: Voir conservation avec Leucidal SF Max | K35: Milie | L35: 10j | M35: 6 mois
B36: MP410 | C36: =VLOOKUP(B36,Liste!A11:O1224,2,0) -> Leucidal SF Max | D36: Lactobacillus Ferment | E36: =VLOOKUP(C36,Liste!B11:P1224,2,0) -> Active Micro | G36: 4 | H36: =VLOOKUP('Gamme bébé'!B36,Liste!A11:O1270,6,0) -> 39.43 | I36: 20kg | K36: Active Micro Technologies Raphaëlle BRUNET-TRON r.brunet@activeconcepts.it | L36: 15j | M36: 12 mois
B37: MP523 | C37: =VLOOKUP(B37,Liste!A12:O1225,2,0) -> Vanilline | E37: =VLOOKUP(C37,Liste!B12:P1225,2,0) -> Diffusions aromatiques | G37: 0.05 | H37: =VLOOKUP('Gamme bébé'!B37,Liste!A12:O1271,6,0) -> 520
B38: MP409 | C38: =VLOOKUP(B38,Liste!A13:O1226,2,0) -> Cosphaderm Sodium LAAS | E38: =VLOOKUP(C38,Liste!B13:P1226,2,0) -> Cosphatec | G38: 1 | H38: =VLOOKUP('Gamme bébé'!B38,Liste!A13:O1272,6,0) -> 94.57
B39: MP113B | C39: =VLOOKUP(B39,Liste!A14:O1227,2,0) -> HV Olive BIO | E39: =VLOOKUP(C39,Liste!B14:P1227,2,0) -> Cauvin | G39: 1 | H39: =VLOOKUP('Gamme bébé'!B39,Liste!A14:O1273,6,0) -> 10.43
B40: MP112 | C40: =VLOOKUP(B40,Liste!A15:O1228,2,0) -> HV Buah Merah | E40: =VLOOKUP(C40,Liste!B15:P1228,2,0) -> DKSH | G40: 0.01 | H40: =VLOOKUP('Gamme bébé'!B40,Liste!A15:O1274,6,0) -> 170
B41: MP010 | C41: =VLOOKUP(B41,Liste!A16:O1229,2,0) -> CosmePhytami Oat | D41: Glycerin (and) Avena Sativa Kernel Extract | E41: =VLOOKUP(C41,Liste!B16:P1229,2,0) -> Alban Muller / CRODA | G41: 1 | H41: =VLOOKUP('Gamme bébé'!B41,Liste!A16:O1275,6,0) -> 32.82 | I41: 5kg | K41: CRODA, Caroline QUENTIN | L41: 3-4 semaines | M41: 36 mois
B42: MP401B | C42: =VLOOKUP(B42,Liste!A17:O1230,2,0) -> Glycerine BIO | E42: =VLOOKUP(C42,Liste!B17:P1230,2,0) -> IES Labo | G42: 9 | H42: =VLOOKUP('Gamme bébé'!B42,Liste!A17:O1276,6,0) -> 6.86
B43: MP350 | C43: =VLOOKUP(B43,Liste!A18:O1231,2,0) -> Gomme Xanthane | E43: =VLOOKUP(C43,Liste!B18:P1231,2,0) -> AMI | G43: 1.2 | H43: =VLOOKUP('Gamme bébé'!B43,Liste!A18:O1277,6,0) -> 23.33
B44: MP403 | C44: =VLOOKUP(B44,Liste!A19:O1232,2,0) -> Acide lactique | E44: =VLOOKUP(C44,Liste!B19:P1232,2,0) -> AMI | G44: 0.6 | H44: =VLOOKUP('Gamme bébé'!B44,Liste!A19:O1278,6,0) -> 6.4
B45: MP000 | C45: =VLOOKUP(B45,Liste!A20:O1233,2,0) -> Eau déminéralisée | E45: =VLOOKUP(C45,Liste!B20:P1233,2,0) -> La Canopée | G45: 52.14
A46: Liniment à la lavande | B46: MP607 | C46: =VLOOKUP(B46,Liste!A21:O1234,2,0) -> Hydroxyde de calcium | D46: Calcium hydroxide | E46: Calmags | F46: NA | G46: 50 | H46: 0.412 | I46: 25kg | K46: Linda Hanke, l.hanke@calmags.de | L46: 15j | O46: Bouillote PET 200ml + chapeau chinois | P46: =SUM(G46:G51) -> 100
B47: MP113B | C47: =VLOOKUP(B47,Liste!A22:O1235,2,0) -> HV Olive BIO | G47: 27.8 | H47: =VLOOKUP('Gamme bébé'!B47,Liste!A19:O1278,6,0) -> 10.43
B48: MP119B | C48: =VLOOKUP(B48,Liste!A23:O1236,2,0) -> Huile de cameline vierge BIO | E48: Bertin | G48: 10 | H48: =VLOOKUP('Gamme bébé'!B48,Liste!A20:O1279,6,0) -> 12.67
B49: MP114B | C49: =VLOOKUP(B49,Liste!A24:O1237,2,0) -> Macérât de lavande bio | G49: 10 | H49: =VLOOKUP('Gamme bébé'!B49,Liste!A21:O1280,6,0) -> 13.1
B50: MP116 | C50: =VLOOKUP(B50,Liste!A25:O1238,2,0) -> Cire de candelilla | G50: 2 | H50: =VLOOKUP('Gamme bébé'!B50,Liste!A22:O1281,6,0) -> 28.9
B51: MP402 | C51: =VLOOKUP(B51,Liste!A27:O1240,2,0) -> Vitamine E | G51: 0.2 | H51: =VLOOKUP('[1]Gamme bébé'!B49,[1]Liste!A16:O1116,6,0) -> #N/A
A53: Sous formule | B53: MP607 | C53: =VLOOKUP(B53,[1]Liste!A10:O1064,2,0) -> #N/A | E53: Brenntag | G53: 0.52 | H53: 11.5
B54: MP000 | C54: =VLOOKUP(B54,[1]Liste!A11:O1065,2,0) -> #N/A | E54: La Canopée | G54: 51.48 | H54: 0.3
C56: 1kg eau de chaux => 10g d'hydroxide de calcium = 1%
A57: Pour 1kg d'eau de chaux, il faut :
A58: 10g de chaux | B58: =10*11.5/1000 -> 0.115 | C58: =SUM(B58:B59) -> 0.412
A59: 990g d'eau | B59: =990*0.3/1000 -> 0.297
A61: Pour 1kg de macérât, il faut :
A62: 85% d'olive | B62: =0.85*7.14 -> 6.069 | C62: =SUM(B62:B63) -> 13.104
A63: 15% de lavande fleurs | B63: =0.15*46.9 -> 7.035

Sheet Soin anti-bouton
A2: Soin anti-bouton
A3: Code MP | B3: Nom commercial | C3: Nom INCI | D3: Fournisseur | E3: Autre fournisseur | F3: % utilisé | G3: Prix €/kg HT | H3: MOQ (kg) | I3: Contact | J3: Gestion DLUO | K3: Tolérance pesée | L3: Packaging
A4: MP000 | B4: =VLOOKUP(A4,Liste!A1:O1214,2,0) -> Eau déminéralisée | C4: Aqua | D4: =VLOOKUP(B4,Liste!B1:P1214,2,0) -> La Canopée | E4: NA | F4: =100-SUM(F5:F16) -> 42.34 | G4: =VLOOKUP('Soin anti-bouton'!A4,Liste!A1:O1260,6,0) -> 0.3 | K4: ± 5% | L4: Roll-on Superlook 10 ml ESOBEA
A5: MP201B | B5: =VLOOKUP(A5,Liste!A2:O1215,2,0) -> Hydrolat Fleur d'Oranger BIO (conservé) | C5: Citrus Aurantium Amara Flower Water (and) Aqua (and) Leuconostoc Radish/Root Ferment Filtrate | D5: =VLOOKUP(B5,Liste!B2:P1215,2,0) -> Gazignaire | E5: Florihana | F5: 15 | G5: =VLOOKUP('Soin anti-bouton'!A5,Liste!A2:O1261,6,0) -> 7.25 | K5: ± 5%
A6: MP401B | B6: =VLOOKUP(A6,Liste!A3:O1216,2,0) -> Glycerine BIO | C6: Glycerin | D6: =VLOOKUP(B6,Liste!B3:P1216,2,0) -> IES Labo | E6: NA | F6: 10 | G6: =VLOOKUP('Soin anti-bouton'!A6,Liste!A3:O1262,6,0) -> 6.86 | K6: ± 1%
A7: MP350 | B7: =VLOOKUP(A7,Liste!A4:O1217,2,0) -> Gomme Xanthane | C7: Xanthan gum | D7: =VLOOKUP(B7,Liste!B4:P1217,2,0) -> AMI | E7: Cosphatec | F7: 0.3 | G7: =VLOOKUP('Soin anti-bouton'!A7,Liste!A4:O1263,6,0) -> 23.33 | K7: ± 0,1%
A8: MP405B | B8: =VLOOKUP(A8,Liste!A5:O1218,2,0) -> Alcool BIO | C8: Alcohol | D8: =VLOOKUP(B8,Liste!B5:P1218,2,0) -> Isnard Trans Alcool | E8: NA | F8: 20 | G8: =VLOOKUP('Soin anti-bouton'!A8,Liste!A5:O1264,6,0) -> 4.25 | K8: ± 5%
A9: MP705 | B9: =VLOOKUP(A9,Liste!A6:O1219,2,0) -> Amiperfect ER | C9: Salicylic acid | D9: =VLOOKUP(B9,Liste!B6:P1219,2,0) -> CRODA | E9: Givaudan/Qmasso | F9: 0.4 | G9: =VLOOKUP('Soin anti-bouton'!A9,Liste!A6:O1265,6,0) -> 330 | H9: 5 | I9: Guilhem COMBES, gcombes@cqmasso.com OU Caroline QUENTIN | K9: ± 0,01% | N9: 1ère prod : 1000 unités
A10: MP503B | B10: =VLOOKUP(A10,Liste!A7:O1220,2,0) -> He Tea tree BIO | C10: Melaleuca Alternifolia Leaf Oil | D10: =VLOOKUP(B10,Liste!B7:P1220,2,0) -> Diffusions aromatiques | F10: 0.16 | G10: =VLOOKUP('Soin anti-bouton'!A10,Liste!A7:O1266,6,0) -> 105 | K10: ± 0,02%
A11: MP508B | B11: =VLOOKUP(A11,Liste!A8:O1221,2,0) -> He Lavande fine BIO | C11: Lavandula Angustifolia Oil | D11: =VLOOKUP(B11,Liste!B8:P1221,2,0) -> Diffusions aromatiques | F11: 0.05 | G11: =VLOOKUP('Soin anti-bouton'!A11,Liste!A8:O1267,6,0) -> 240 | K11: ± 0,02%
A12: MP507B | B12: =VLOOKUP(A12,Liste!A9:O1222,2,0) -> He Orange sanguine BIO | C12: Citrus Aurantium Dulcis Peel Oil | D12: =VLOOKUP(B12,Liste!B9:P1222,2,0) -> Campisi Citrus | F12: 0.04 | G12: =VLOOKUP('Soin anti-bouton'!A12,Liste!A9:O1268,6,0) -> 68 | K12: ± 0,02%
A13: MP706 | B13: =VLOOKUP(A13,Liste!A9:O1222,2,0) -> Glucono-Delta-Lactone | C13: Gluconolactone | D13: =VLOOKUP(B13,Liste!B9:P1222,2,0) -> AMI | F13: 8 | G13: =VLOOKUP('Soin anti-bouton'!A13,Liste!A9:O1268,6,0) -> 6.18 | H13: 25 | I13: Armoni.BODIN@ami-ingredients.fr | K13: 0.02
A14: MP015 | B14: =VLOOKUP(A14,Liste!A10:O1223,2,0) -> Opuntia Biocomplex SH | C14: Opuntia Ficus-Indica stem extract (and) Maltodextrin | D14: Bionap | F14: 1.7 | G14: =VLOOKUP('Soin anti-bouton'!A14,Liste!A10:O1269,6,0) -> 90 | H14: 5 | I14: Marco MOLARO m.molaro@bionap.com | K14: ± 0,5%
A15: MP403 | B15: =VLOOKUP(A15,Liste!A11:O1224,2,0) -> Acide lactique | C15: Lactic acid | D15: =VLOOKUP(B15,Liste!B11:P1224,2,0) -> AMI | F15: 0.01 | G15: =VLOOKUP('Soin anti-bouton'!A15,Liste!A11:O1270,6,0) -> 6.4 | K15: ± 0,01%
A16: MP400 | B16: =VLOOKUP(A16,Liste!A12:O1225,2,0) -> Leucidal Liquid | C16: Leuconostoc Radish/Root Ferment Filtrate | D16: =VLOOKUP(B16,Liste!B12:P1225,2,0) -> Active Concept / Active Micro | F16: 2 | G16: =VLOOKUP('Soin anti-bouton'!A16,Liste!A12:O1271,6,0) -> 35.92 | K16: 0.02
F17: =SUM(F4:F16) -> 100
M23: =SUM(F23:F29) -> 0
M30: =SUM(F30:F42) -> 0
M43: =SUM(F43:F49) -> 0
